{"isMapUser":false,"isExist":true,"basicInfo":{"cid":1362462523,"placenamefull":"제주봄카페&스테이 전기차충전소","phonenum":"02-1833-8017","address":{"newaddr":{"newaddrfull":"검은여로130번길 68-16","bsizonno":"63598"},"region":{"name3":"토평동","fullname":"제주특별자치도 서귀포시 토평동","newaddrfullname":"제주특별자치도 서귀포시"},"addrbunho":"329-1"},"wpointx":403834,"wpointy":-67300,"roadview":{"panoid":1070311968,"tilt":3,"pan":321.0,"wphotox":403912,"wphotoy":-67379,"rvlevel":2},"cateid":"18428","catename":"전기자동차 충전소","cate1name":"교통,수송","feedback":{"allphotocnt":0,"blogrvwcnt":0,"kascnt":0,"comntcnt":0,"scoresum":0,"scorecnt":0},"source":{"date":"2019.11.26."},"isStation":false},"comment":{"placenamefull":"제주봄카페&스테이 전기차충전소","allComntcnt":0,"kamapComntcnt":0,"kaplaceComntcnt":0,"daumComntcnt":0,"scoresum":0,"scorecnt":0,"currentPage":1,"prevPage":-1},"findway":{"x":403834,"y":-67300,"busDirectionCheck":false}}