{"isMapUser":false,"isExist":true,"basicInfo":{"cid":1820359262,"placenamefull":"오르다","mainphotourl":"http://t1.daumcdn.net/place/98DAAB2CB28A46669FF0B142E2AA0B99","address":{"newaddr":{"newaddrfull":"한도로 269-37","bsizonno":"63643"},"region":{"name3":"성산읍 성산리","fullname":"제주특별자치도 서귀포시 성산읍 성산리","newaddrfullname":"제주특별자치도 서귀포시 성산읍"},"addrbunho":"308"},"wpointx":484988,"wpointy":-6869,"roadview":{"panoid":1088746959,"tilt":-3,"pan":286.0,"wphotox":485112,"wphotoy":-6922,"rvlevel":2},"cateid":"86","catename":"카페","cate1name":"음식점","englishname":"ORDA","feedback":{"allphotocnt":1566,"blogrvwcnt":115,"kascnt":5,"comntcnt":7,"scoresum":25,"scorecnt":7},"openHour":{"periodList":[{"periodName":"영업기간","timeList":[{"timeName":"영업시간","timeSE":"08:00 ~ 22:00","dayOfWeek":"매일"}]}],"offdayList":[{"holidayName":"연중무휴"}],"realtime":{"holiday":"N","breaktime":"N","open":"Y","moreOpenOffInfoExists":"Y","datetime":"20191202173100","currentPeriod":{"periodName":"영업기간","timeList":[{"timeName":"영업시간","timeSE":"08:00 ~ 22:00","dayOfWeek":"매일"}]}}},"metaKeywordList":["이국적인","피맥"],"source":{"date":"2019.09.24."},"isStation":false},"s2graph":{"gender":{"labels":["남","여"],"data":[1817,3516]},"torosImpressionId":"toros_kakaomap_sim_alpha","day":{"labels":[0,1,2,3,4,5,6,7,8,9,10,11,12,13,14,15,16,17,18,19,20,21,22,23],"avg":[16,12,4,0,2,1,7,10,15,34,52,54,66,57,56,66,57,56,55,42,30,24,22,23],"monday":[4,10,6,0,12,2,4,4,16,22,38,56,48,68,24,24,30,20,14,10,0,8,18,18],"tuesday":[16,8,0,0,0,0,8,6,18,28,16,48,26,22,30,36,62,44,60,12,28,60,10,40],"wednesday":[8,0,2,0,0,0,12,4,6,10,8,32,30,50,36,56,12,56,14,6,10,16,0,4],"thursday":[14,2,12,0,0,0,14,0,2,6,58,30,4,18,28,28,36,26,56,58,28,20,26,36],"friday":[8,19,4,0,6,4,11,2,22,12,83,96,190,109,140,100,73,96,131,94,60,31,52,30],"saturday":[24,18,4,0,0,2,2,42,30,92,98,64,96,70,86,106,134,68,58,56,30,22,36,18],"sunday":[44,30,0,0,0,0,4,14,14,68,64,56,68,62,54,116,54,86,58,60,54,16,14,20],"max":190,"wheremax":"friday"},"nearPlaceList":[{"placenamefull":"수마","photourl":"http://t1.daumcdn.net/localfiy/2143D62C5F98405987C607618D166F6F","confirmid":83691382,"catename":"카페"},{"placenamefull":"빽다방 제주성산일출봉점","photourl":"http://t1.daumcdn.net/place/BDF9C18CDFF04481BEBC5F2AE394D1DE","confirmid":27095583,"catename":"빽다방"},{"placenamefull":"카페코지","photourl":"http://t1.daumcdn.net/place/52FCAB68F84748B9A76964155D5B018D","confirmid":17880473,"catename":"카페"},{"placenamefull":"성산옥탑","photourl":"http://t1.daumcdn.net/place/AC5AFDF6297D4592A2D81169E80C2FDC","confirmid":137722576,"catename":"양식"},{"placenamefull":"스타벅스 성산일출봉점","photourl":"http://t1.daumcdn.net/cfile/2508F24955E006C226","confirmid":18143017,"catename":"스타벅스"},{"placenamefull":"바다풍경","photourl":"http://t1.daumcdn.net/place/FFDE0F3A5ABD41B586D1C8E8AC04DEFC","confirmid":10412287,"catename":"해물,생선"},{"placenamefull":"성산59","photourl":"http://t1.daumcdn.net/place/E69240D5180B43E6A77FB0FD07F93C26","confirmid":27391818,"catename":"와인바"},{"placenamefull":"성산회관","photourl":"http://t1.daumcdn.net/cfile/2721A54E576A18152B","confirmid":27100697,"catename":"한식"},{"placenamefull":"성산카베츠","photourl":"http://t1.daumcdn.net/place/4A329999836C4129BB48D0A690AFBCEB","confirmid":1773032132,"catename":"돈까스,우동"}],"age":{"labels":["~20","30","40","50~"],"data":[3587,1348,266,132],"max":3587},"status":"Y"},"blogReview":{"placenamefull":"오르다","moreId":19697271,"blogrvwcnt":115,"list":[{"blogname":"Pluck the day","blogurl":"http://blog.naver.com/sa_rang_kkun_mrj","contents":"안녕하세요 :) 언제쯤 제주도 여행 이야기를 끝낼 수 있을까 생각하면서 매일매일 제주도의 꼭 가야할 곳들을 끄적여보고 있어요 그 중에서 오늘 소개시켜드리고 꼭 추천하고 싶은 곳 이있어요 바로 성산일출봉 옆 오르다 카페 입니다 이 카페는 맛있는 먹거리들 보다는 성산일출봉과 제주의 바다를 한눈에 바라보면서 커피를 즐길 수 있는 곳으로 유명한 곳이예요 저도 여기는 제가 찾아서 발견한 곳이 아니라 제주도 커뮤니티에서도 추천을 많이 하는 곳이라서 가보았습니다 이 곳은 이미 성산일출봉을 가면 꼭 가야하는 관광지 & 코스인 카페라 사람들이 많았어요 위치는 바로 성산일출봉 입구에서 차로 5분도 안걸리는 거리에 있습니다 대부분 차로 오시는 카페라서 그런지 주차장도 크게 위치","outlink":"http://blog.naver.com/sa_rang_kkun_mrj/221720376836","date":"2019.11.27.","reviewid":"19723728","title":"제주 오르다 카페 성산일출봉 카페 천국의계단","isMy":false},{"blogname":"째유의 일상","blogurl":"http://blog.naver.com/kaabdgg123","contents":"안녕하세요 째유입니다 ~!~! 저는 오르다 카페 왔어요 !!!!!!!!!!! #오르다카페 #제주도카페 주차공간 당연있고 ! 버거 먹으로 와찌요 야외공간도 있구 수영장도 있네요 ! 이런 분위기 취저 탕탕 ,,, 제주도 또 가구시퍼,,,,,,,,,,,,,,,,,,, 빵이 몇개 없어요 우울해,,,, ㅠ ㅠ ㅠ ㅠ 10시부터 6시까지입니다 ! 딱 6시 안쪽에 와서 다행히,, 일출봉버거 주문할수있었어요 #일출봉버거 비쥬얼 미쳐따,, ㅁㅊㄷ!!!!!!!!!! 저기 퍼져있는거 치즈 인데 맛있어요 ㅠㅠㅠㅠㅠ 감튀도 있고 빵도 졸깃하늬 구-웃 !!!!!!!!!! 와 !!! 밖에서 사진찍으니 진짜 이뿌다 ㅠ 나중에 이런거 짓고 살구싶다ㅠ ㅠ 버거가 나왔구 아주 맛있게 먹었습니당 ㅎㅎㅎㅎㅎ 버거 어느정도 먹구","outlink":"http://blog.naver.com/kaabdgg123/221719166458","date":"2019.11.26.","reviewid":"19717518","title":"<여행>제주도오르다/오르다카페/오르다/카페스타그램/제주오르다/오르다후기/제주카페추천/제주도카페/오르다카페후기/제주도햄버거/제주수제버거추천","photoList":[{"orgurl":"http://postfiles8.naver.net/MjAxOTExMjNfMjMy/MDAxNTc0NTE1MzMwMjE0.I5B-XZemwgMfuRFe9Eh1JyTJC-xV237VzGsG-l99DYAg.PJ7UEXBpBDUnTBFrnHdfUF9aKAH8EgO0-h9ZUp_-fjog.JPEG.kaabdgg123/2019-08-12-17-41-56-218.jpg?type=w773"},{"orgurl":"http://postfiles2.naver.net/MjAxOTExMjNfMjU3/MDAxNTc0NTE1MzMxNDQ4.raUw8IKES1lFpmIBd74pi7_4LZxYV0vojVlHzTmdIeEg.KqNjayGwIWsYriNTPGlz6I1t8MLvGKM_427ulqsVt6Eg.JPEG.kaabdgg123/2019-08-12-17-42-03-347.jpg?type=w773"},{"orgurl":"http://postfiles16.naver.net/MjAxOTExMjNfMjM2/MDAxNTc0NTE1MzMyNTcx.2Y1U1BWSzEOtYW03Y8RppW394krJPjfSgP8t6yKi04kg.YagVYZ5BjneOr7Gnz_PaPxcFpfi-vYwyXtDGZuhGysMg.JPEG.kaabdgg123/2019-08-12-17-42-27-925.jpg?type=w773"},{"orgurl":"http://postfiles12.naver.net/MjAxOTExMjNfMTk0/MDAxNTc0NTE1MzM0OTQ3.furfvngw1NVWm69k0IsWFk289XHaix2l0Tc34jRi7Tcg.wphHchw16sjz8H_LKunlUAkJQRtxc99ijFsADxfNn9Eg.JPEG.kaabdgg123/2019-08-12-17-42-11-931.jpg?type=w773"},{"orgurl":"http://postfiles10.naver.net/MjAxOTExMjNfMjMx/MDAxNTc0NTE1MzMzNzcz.9IOUtvcCtN8Q3jEEoCfowU8ZVVO1lWbWTgeebgtjdQEg.4B-E3Rp_L3U8PfX-VJpcpsNsd2t3N40fK8We7fJp6ogg.JPEG.kaabdgg123/2019-08-12-17-42-18-758.jpg?type=w773"},{"orgurl":"http://postfiles8.naver.net/MjAxOTExMjNfMjcz/MDAxNTc0NTE1MzM3Mzkw.cqrklr3CaUti0RJ2sJrEkssa2E_xP20dzWEUJ9t1lzkg.43KKZGEW6sfkYVccV4Keb0pMTMtThqdT9Z0ykASVHyMg.JPEG.kaabdgg123/2019-08-12-17-42-09-215.jpg?type=w773"},{"orgurl":"http://postfiles12.naver.net/MjAxOTExMjNfMTQx/MDAxNTc0NTE1MzQyMDU4.FMRfWTE_9FqFEuxYbpiDh8Y4vHyd7G2TGv9_LUY7i34g.0jL-WwMuWIbvtkKOernfaTLNjaYz8oVSr8TEx4vnAGgg.JPEG.kaabdgg123/2019-08-12-17-58-08-192.jpg?type=w773"},{"orgurl":"http://postfiles5.naver.net/MjAxOTExMjNfMTkw/MDAxNTc0NTE1MzQwOTAy.wUFuPtwkNxgUzp4mQOykeHuElju6F36ZBNgxB0N_VJwg.ShQCSLnwpYdZViKLdRGgBPKla2o_lzTNjdijLROuOEcg.JPEG.kaabdgg123/2019-08-12-17-58-24-301.jpg?type=w773"},{"orgurl":"http://postfiles4.naver.net/MjAxOTExMjNfMTQ5/MDAxNTc0NTE1MzQ1NzY5.RMniE0GQHJnT0FyfLfygeXbhe8Gfb9KFBd00AfCd1f0g.HffNQsD-uldsZ44DpVozhomG_T29bFFU3ab2yb0k7ZAg.JPEG.kaabdgg123/2019-08-12-17-42-41-454.jpg?type=w773"},{"orgurl":"http://postfiles15.naver.net/MjAxOTExMjNfMTQg/MDAxNTc0NTE1MzQ4MjQ2.v-Eey8dc6d1AdCK2phO5SgCwGMGg5JqJTib52y0APewg.E9cSjN2nLhMR8E6MMiEGmGIDp_a1A303FWdgaEGPfSIg.JPEG.kaabdgg123/20190812_183136.jpg?type=w773"}],"isMy":false},{"blogname":"돌고돌아 글을 남기었지","blogurl":"http://blog.naver.com/yaho24","contents":"© YHBae, 출처 Pixabay 제주 오르다카페는 성산일출봉과 우도가 한눈에 보이는 제주에서 경관좋은 카페 중 하나인데요, 이번에는 성산쪽을 다녀와서 적어봅니다. 일단 시키고 기다리면서 볼거리가 있어서 작년에 왔었을 때 다녀온 성산일출봉 정상을 좋아하는건 아니고 1층 카페 고객이라면 이용 가능하다. 작년에 이어 20 10월 25일 금요일 요즘은 숙소들이 다 씻고 티저 기다리면서 풍경을 직원들은 늘 짐을 보내본 적 없는데 먹방영상은 여기에서 호야 아까운 망고스무디 망설이는 중이었는데 제주도 자연 휴양림으로 다녀왔습니다. 오르다 토깽이 금요일에 링거 맞았더니 그 옆에 앉아보기 바다 이게 예사롭지 않은 채 살짝 더 가고 싶은 마음이 환해지는 느낌 빨대가 커서 신기했네요. 제주 멜젓은 맛이 이상할까 봐 걱정했는","outlink":"http://blog.naver.com/yaho24/221712599281","date":"2019.11.19.","reviewid":"19645645","title":"제주 오르다카페 이쁜 경관과 맛있는 햄버거 여행 다녀오다","photoList":[{"orgurl":"http://postfiles13.naver.net/MjAxOTExMTlfMTI3/MDAxNTc0MTYxMDMzMjk1.-ef8mPzwb9edDg-_UcQyTonvO_GOXGtFEepn3dSEpdYg.IidrIQ76ixyYcHYIWhMxdmN7otsM-uhwfR7O2bGZN-cg.JPEG.yaho24/52e2d3454857a814ea89807fc62d327a1522dfe05455714e722679d0_1280.jpg?type=w966"},{"orgurl":"http://postfiles6.naver.net/MjAxOTExMTlfMTc0/MDAxNTc0MTYxMDQ1NTkx.dfRSUFZ3zCKYsRjIOFgAhL1DBE098PeSGDFwYylJnf0g.9VZZsOoZmOpCQIYjW5TlDky2l0P3z3MBc3ZRZV4wQR4g.JPEG.yaho24/photo-1556742517-fde6c2abbe11.jpg?type=w966"},{"orgurl":"http://postfiles1.naver.net/MjAxOTExMTlfMjAz/MDAxNTc0MTYxMDY0NDc2.8l5g-U7ytaMt0QJF4vr2t43jRrbj4xip68czJAnnG1Qg.Gr2x5IwtMCxF3nE16MpyZBHfwpurRlAuZmQKRbCo6fMg.JPEG.yaho24/57e8d241425aa414ea89807fc62d327a1522dfe05455704a7c2772d6_1920.jpg?type=w966"},{"orgurl":"http://postfiles13.naver.net/MjAxOTExMTlfNzkg/MDAxNTc0MTYxMDc5NTEw.UjcgzpowT7AmIyrXobV4Idl7pZkp0zM0NH4P6DYhkFYg.mpL2LptgGVLCMj8LIsV9jCkRnYYaJQs-Q3L77YNXwbUg.JPEG.yaho24/54e4d7464952af14ea89807fc62d327a1522dfe05455704a742a72d3_1280.jpg?type=w966"},{"orgurl":"http://postfiles1.naver.net/MjAxOTExMTlfMjUx/MDAxNTc0MTYxMDg4NDM1.UCw7Cxe_BWKTk82iia4oY_cXnJo-apBU2weOcEMWEHIg.27ivgEi6UlrXVxQlT-HMzxAGEUJBgjwxZyukneHnGX8g.JPEG.yaho24/photo-1502849394214-c4b6352145ee.jpg?type=w966"},{"orgurl":"http://postfiles6.naver.net/MjAxOTExMTlfMTAg/MDAxNTc0MTYxMDkyMTcx.Umbj3c3-SeIQrbumJV7rTrC73BYpdaQN38FafpMvudQg.qUmd8zG-fNWzt8rt9LWZqIVhZziMF6xSvjqj48t4vKog.JPEG.yaho24/photo-1514134583630-250e42c36dbd.jpg?type=w966"}],"isMy":false},{"blogname":"유진쓰 이야기 '◡'","blogurl":"http://blog.naver.com/aa8122","contents":"제주도 성산일출봉 뷰가 예쁜, 오르다 카페 (ORDA) #제주도카페 #성산일출봉카페 포스팅이 계속계속 밀리는 제주여행 :! 제주여행의 이튿날 아침, 제주김만복에서 아침을 먹고 찾아간 오르다카페에요. 카페 가는 길목에도 차 세워두고 잠깐 사진찍고, 경치를 구경할 만한 곳들이 많았어요. 저희는 바로 카페로 갔지만 시간 여유 있으신 분들은 느긋하게 구경하시면서 카페가시는 것도 좋은 방법일 것 같아요. #오르다카페 너무 일찍 도착한 덕분에 아직 야의 테이블들은 세워져 있지도 않았어요 ㅎㅎㅎㅎㅎㅎㅎ 부지런부지런. 카페 내부에서도 햇빛 강하게 받으며 야외경치를 즐길 수 있어요. 다시봐도 예쁜 하늘이에요. 너무 예쁜 제주. ","outlink":"http://blog.naver.com/aa8122/221712003401","date":"2019.11.19.","reviewid":"19640150","title":"[제주] 엄마랑 제주도여행 - 제주도카페 / 성산일출봉 뷰 / 오르다카페","photoList":[{"orgurl":"http://postfiles5.naver.net/MjAxOTExMTlfMTc4/MDAxNTc0MTI1MDI2MTQ3.M0OiWbrOERkK2D2RzYR7NdSEAcqXJpo0UJQKhFRdXQUg.nVy6FnXMkG0OqB_3v0NTPxCPSzRdYsBLfyJxQ3raqAQg.JPEG.aa8122/SE-e67a33d7-f378-4916-8260-83bd306c5385.jpg?type=w966"},{"orgurl":"http://postfiles8.naver.net/MjAxOTExMTlfMjE4/MDAxNTc0MTI1MDI3MTUw.acb1xUSsWTW3hT1tShn1972VcFXWZre_I_APUpLAswUg.Eb6LW1TTAsJn4mTncL_3_RsDIZMVMpL_P11In0KFoWog.JPEG.aa8122/SE-6d076067-29fe-4745-90c8-f0d6b7dfab28.jpg?type=w966"},{"orgurl":"http://postfiles11.naver.net/MjAxOTExMTlfMTk5/MDAxNTc0MTI1MDI3OTA5.yuUUfjJHZ55junQvtgQDvwNzTVuf6j-wEgsvXrFcU4Ig.rocM48CBxMJJjbrhlF8lfRcOCauOJ4YV2m0awHx6CZgg.JPEG.aa8122/SE-18c6d016-dd59-4f09-be52-38824b6b1485.jpg?type=w966"},{"orgurl":"http://postfiles5.naver.net/MjAxOTExMTlfMTYg/MDAxNTc0MTI1MDI4Nzk3.QV5kHmJ1xGqNEqY1A4RYBgJY2iBajIRUVaKbhOR9gykg.aXApDeQp3vY3l_aEMv1cpvlEirchl6Vp_-kuOOO4wbEg.JPEG.aa8122/SE-01b63768-5465-4304-802d-06fc45cdf6f5.jpg?type=w966"},{"orgurl":"http://postfiles16.naver.net/MjAxOTExMTlfMTUz/MDAxNTc0MTI1MDI5NzEw.a6KhJHsDgL8OaT2iLB64VP1ZvRggeKm8o4B_ZguNFB0g.OlYPfR4GMEv5q9sxGu4dFmZoAgnP1PzjCeUhoAOLWNwg.JPEG.aa8122/SE-58cfba81-e81c-4803-960f-d3577803a6a2.jpg?type=w966"},{"orgurl":"http://postfiles8.naver.net/MjAxOTExMTlfMTQg/MDAxNTc0MTI1MDMwNDkz._xmkFVxTSQGKJCdAgRit-TXxrvRpJxGpcUohf9pKaR4g.Eae8xZOBD2cJ0Z4-lBA0cbB-6x9a2F_pasJPN1XX2Wsg.JPEG.aa8122/SE-4e399b57-6046-47bf-987d-b25b5afb2630.jpg?type=w966"},{"orgurl":"http://postfiles11.naver.net/MjAxOTExMTlfMjA2/MDAxNTc0MTI1MDMxNDM5.jFf7o0tMxNaP6mFntAAwNEGM1DZMWUfWemC5JgKHD0sg.7XNbuM7HXsdCd0stj4l9euV7_5qR_DCUWfXh62FD_q4g.JPEG.aa8122/SE-33d97ff1-b287-4481-8e20-2870cbe769ed.jpg?type=w966"},{"orgurl":"http://postfiles5.naver.net/MjAxOTExMTlfNjYg/MDAxNTc0MTI1MDMyMjU4.l_WSZ-L-sTXYy_ohRlqNsVddfmj5X8JdfTvu694K3Fwg.gHO0ht4XkJ2RNCgoJYYWvtbGUJOcTo6bIkYDAp6q_k8g.JPEG.aa8122/SE-dca0e71b-0532-4763-8c9b-49603d74f7b9.jpg?type=w966"},{"orgurl":"http://postfiles11.naver.net/MjAxOTExMTlfMSAg/MDAxNTc0MTI1MDMzOTAy.0ERXIoH8He19cBjmxDuqoXGSaXLTzbOFi7-mev-zrbIg.X7OpR61D_-dhhe9ZPEgBnoihmBT_Uk2s968ML0cFTZog.JPEG.aa8122/SE-7d692ed0-b37c-4332-9502-2f3f04727691.jpg?type=w966"},{"orgurl":"http://postfiles15.naver.net/MjAxOTExMTlfMTI3/MDAxNTc0MTI1MDM0NzQy.tAj4CNry1S2pGJ9OKDvlwRkJZdbNbZ_QMRWX9yR6Zywg.S0al6LNDsjxAfw5ZE1h_97Ag803V2Pi-p1RCvli86Pcg.JPEG.aa8122/SE-bf9addc4-91f7-4f5f-bee1-9e4852ea8613.jpg?type=w966"}],"isMy":false},{"blogname":"몽상가 중독증세의 여행이야기","blogurl":"http://blog.naver.com/alfyoun","contents":"제주 오르다 카페 성산일출봉 오르다 카페에서 인생 사진 남기기~ 제주 오르다 카페 제주 산방산에 마노르블랑이 있다면 성산일출봉에는 오르다가 있다! 무슨 말이냐고요?^^ 제주 산방산과 성산일출봉은 서귀포시 서쪽과 동쪽 끝자락에 위치한 유명 관광지이며 이 두 곳을 대표하는 카페가 바로 마노르블랑과 오르다 카페입니다. 마노르블랑에는 예쁘게 가꾸어진 핑크뮬리 정원이 있고, 오르다카페는 멋진 바다 뷰와 색다른 추억을 만들 수 있는 '천국의 계단' 포토존이 있는 카페입니다. 성산일출봉과 우도 중간에 위치하여 최고의 뷰를 자랑하는 트로피컬 라운지 오르다 카페! 이미 오르다 천국의 계단은 인싸~ 제주 여행 마지막 날 가족과 함께 오르다 카페에서 커피도 마시고 천국의 계단에 올라 ","outlink":"http://blog.naver.com/alfyoun/221706352713","date":"2019.11.13.","reviewid":"19615159","title":"제주 오르다카페 인생 사진 남기기","photoList":[{"orgurl":"http://postfiles7.naver.net/MjAxOTExMTNfMjYx/MDAxNTczNjEwNzgyMTAz.-cmi34QOIcZTAlnYfqwJ5AKhoCS777r-jyjNWdNYIqIg.R2J_AYRYwo6JCFaphPXgJo2mmd09-5ROZ7ZXaDRHm-wg.PNG.alfyoun/IMG_2683.png?type=w966"},{"orgurl":"http://postfiles1.naver.net/MjAxOTExMTNfMTgz/MDAxNTczNjExMDU5NDUy.OQZuT7-m-MMOQ_GpkTQ3UI5rUavfJqOOqFiyRvDZenkg.wfMpehatbxxEMA-QB86s3cL8JwNWTiPfsjwToY5TF0wg.PNG.alfyoun/IMG_2693.png?type=w966"},{"orgurl":"http://postfiles15.naver.net/MjAxOTExMTNfMTEz/MDAxNTczNjExMTI2NTQw.ydUKx4qWnZ107SGPbQVvvu422-WU9lFkX-hY2zPGLcMg.9_0Tf8iN4tnQpM_oVapVsWaR9yDMddoHZQw5VCfjh2Ug.PNG.alfyoun/IMG_2768.png?type=w966"}],"isMy":false},{"blogname":"#","blogurl":"http://blog.naver.com/kkii8722","contents":"안녕하세요 호덕이예요 오늘 가져온 포스팅은 카페 후기인데요! 넓은 야외와 주차시설마저 준비가 잘된 카페입니다. 다들 SNS 를 통해서 보셨을수도 있어요 그래서 거기가 어디냐면 제가 다녀온 제주도 카페 카페 오르다 카페 외관 주변 풍경 (성산일출봉) 사진속 보이는 오름이 성산일출봉 입니다 . 일출봉 근처 해안가에 위치하여 있어서 사진찍기에도 적합한 곳이라고 생각이 들어요 ! 역시 포토존 대장인 천국의계단 이라고 불리는곳에서 사진을 가장많이 찍더라구요 . 야외에도 테이블 자리들이 정말 많았어요. 바람이 다소 많이 불어서 문제였긴 했지만 카페 내부 내부는 테이블 사이 간격들이 좁은곳과 단체석 등으로 나눠진거같더라구요. 내부도 야외와 마찬가지로 자리는 많았습니다. 평일에다가 퇴근시간 전에 갔는데도 사람아 많더라","outlink":"http://blog.naver.com/kkii8722/221701928447","date":"2019.11.08.","reviewid":"19697271","title":"제주도 제주시 하늘계단 카페 \"오르다\" 카페","photoList":[{"orgurl":"http://postfiles1.naver.net/MjAxOTExMDhfODYg/MDAxNTczMTk4MDA4MTE3.BtSIvygzRG-RrfNRZg6hVFC8YwMl1Yz1pViLdncnJH8g.YPQWXMWlF82hwBvQgoP9XfxHf0QwAmIHVz2G4dy5vm8g.JPEG.kkii8722/1573198009884.jpg?type=w773"},{"orgurl":"http://postfiles15.naver.net/MjAxOTExMDhfMjY5/MDAxNTczMTk3NjAzMzg0.qVG7kyAA3zjXaJVeOFhHtzElgVX4dJwluPhckryAmGAg.O-9fqeQmepWidKGLt8gfIpfimGaGKLjgukYv_o_k9hcg.JPEG.kkii8722/1573197605088.jpg?type=w773"},{"orgurl":"http://postfiles11.naver.net/MjAxOTExMDhfMTA3/MDAxNTczMTk3NjA2MDUw.3kVN6wdzvCwT6enKV2Ydy7Kv3EYXne2e5-PnxT1KwC0g.vC_VHVlSj3ElvefJLBLUQShtyx6li5PhhwW2YMKQFZwg.JPEG.kkii8722/1573197607768.jpg?type=w773"},{"orgurl":"http://postfiles15.naver.net/MjAxOTExMDhfMjc3/MDAxNTczMTk3NjA3Mzcy.hw7hwDTInQ5fRnGCzzmIazaE3_FBQ3KNnqJ4zjPoBl0g.BvM_UaumYcKZs-LyjUe2jsSbsouFIxmZtLd8JCWZMUMg.JPEG.kkii8722/1573197609089.jpg?type=w773"},{"orgurl":"http://postfiles3.naver.net/MjAxOTExMDhfMTE0/MDAxNTczMTk3NjA4NjI4.pojy5hVHRfaVmTQcy7QT_gGpooeTqA-yfjXlSjc-KZIg.QI5EB4gDnNiEcUj3csFfiRXYXT5A16QiXeorJHSufe0g.JPEG.kkii8722/1573197610357.jpg?type=w773"},{"orgurl":"http://postfiles13.naver.net/MjAxOTExMDhfMTAg/MDAxNTczMTk3NjEwMDI5.6tH3LML9PPdjy4GNhjf1r3rK9HKFIqBTU7nvYN0MYCUg.k3nn96RfcJqAW_99VYJCBzkVp_lCDrMIHVuOIG5_yPYg.JPEG.kkii8722/1573197611847.jpg?type=w773"},{"orgurl":"http://postfiles2.naver.net/MjAxOTExMDhfMjAw/MDAxNTczMTk3NjExMjU1.TZX63zX7-AkYQNBKupC72fXIOO4SKQO8-I7a81cRZ6og.E2Npgnn0fohkxu9Pkp0OM8m0SFXmEE-98Tf8MxuFhJUg.JPEG.kkii8722/1573197612935.jpg?type=w773"},{"orgurl":"http://postfiles8.naver.net/MjAxOTExMDhfMjg3/MDAxNTczMTk3NjEyNDEz.mvFqcauCuHb38Tnnl1dDCgy6PBu7ckHT7SYPcRKArmsg.Vpzss33KwN0sBcawNpgTJRoyY_XyKlxSx0p43lSCWTwg.JPEG.kkii8722/1573197614191.jpg?type=w773"},{"orgurl":"http://postfiles16.naver.net/MjAxOTExMDhfNTAg/MDAxNTczMTk3NjEzNzAz.NJyg_0tggS6KJSXsHbe3q41pvTHTTT9i1JcYmWVCKegg.DtDxz7MSIkmpTK0GUArn-t9_clZaNa1_oLeqq12So2cg.JPEG.kkii8722/1573197615463.jpg?type=w773"},{"orgurl":"http://postfiles2.naver.net/MjAxOTExMDhfMjcy/MDAxNTczMTk3NjE0OTYx.rxhDnpOsmgXL68k4o-QRQ-z37ydc92SkfzjIFpdcZHwg.bVziodRzeMHFb_3bx8FjS-FdXfsUCA2qeh_-7d6gbi4g.JPEG.kkii8722/1573197616742.jpg?type=w773"}],"isMy":false}]},"kakaoStory":{"placenamefull":"오르다","kascnt":5,"list":[{"storyid":"103229430538022802","creator":"이은주","outlink":"https://story.kakao.com/_JQnmP/d5D80w39uP0?from=kakaomap","image":"http://dn-l0-story.kakao.co.kr/dn/cb7gXI/hyDTW6Ja72/LylaC03Z5pnSNO4HYspJ4k/img.jpg?width=1920&height=1276&avg=%25238d8d8e&v=2","imgcnt":20,"body":"#오르다 #성산카페오르다 #성산카페 #천국의계단 #제주천국의계단 #오르다카페 ❣❣ 제주여행한다면 ᆢ이곳을 강추 하고싶다 ᆢ 진짜 멋진 뷰를 가진곳 ~~~ #제주카페","date":"2019.12.01."},{"storyid":"102993858170096419","creator":"jju","outlink":"https://story.kakao.com/hj0704j/JUcKi8QcsPA?from=kakaomap","image":"http://dn-l0-story.kakao.co.kr/dn/jRz1v/hyDjlMphx4/zTb6KRDPgSFKd6UvI5oAQK/img.jpg?width=862&height=787&avg=%2523c6b4cc&v=2","imgcnt":1,"body":"❤부모님❤외할머니❤큰이모❤둘째이모❤사촌큰언니❤ 감사합니다❤ 감동아~ 예쁘고 건강하게 태어나줘~사랑해♡ #아기선물 #임신8개월 #예비맘 #태명 #딸맘","date":"2019.10.20."},{"storyid":"102896035891876818","creator":"jju","outlink":"https://story.kakao.com/hj0704j/EKx8WqiJEo0?from=kakaomap","image":"http://dn-l0-story.kakao.co.kr/dn/dLCeB/hyC5hhQsfd/AGCDqw9NKpJWZkxKAiaMI0/img.jpg?width=1440&height=1920&avg=%2523958780&v=2","imgcnt":5,"body":"태풍은 무사히 지나가고 해가쨍쨍 ☀️☀️ 맛점하세요 ~^^ #제주고등어회 #제주갈치회 #제주통갈치조림 #성게미역국 #전복 #돌문어 #황게 #한라산소주 #오르다카페 #제주예쁜카페 #제주수제버거 #제주화산버거 #제주도맛집 #제주성산일출봉","date":"2019.10.03."},{"storyid":"102009223785675698","creator":"하정효","outlink":"https://story.kakao.com/_fShLv/EKfkrNOoCm0?from=kakaomap","image":"http://dn-l0-story.kakao.co.kr/dn/cqyKfM/hyAVuSEixO/9VHkHZY26Z6bYwxeKjrRP1/img.jpg?width=1564&height=1564&avg=%25238d8182&v=2","imgcnt":1,"body":"4/23 ~ 4/27 _ JEJU 카페 오르다 [성산일출봉]","date":"2019.04.29."},{"storyid":"100739530213292450","creator":"ranicho","outlink":"https://story.kakao.com/_5Ywiq2/eXUbHby6Ij0?from=kakaomap","image":"http://dn-l0-story.kakao.co.kr/dn/dyIYw7/hyxuY31xit/P3bMK2X1vyKWYZ4qbMzy9k/img.jpg?width=1280&height=1707&avg=%252386766b&v=2","imgcnt":1,"body":"제주 코코넛 쉐이크#성산카페#오르다카페#오르다라운지#성산일출봉카페#제주코코넛#코코넛쉐이크#트로피칼라운지","date":"2018.09.17."}]},"comment":{"placenamefull":"오르다","allComntcnt":7,"kamapComntcnt":7,"kaplaceComntcnt":0,"daumComntcnt":0,"scoresum":25,"scorecnt":7,"currentPage":1,"pageList":[1,2],"list":[{"commentid":"1282161","contents":"","point":4,"username":"유즈","profile":"http://th-p.talk.kakao.co.kr/th/talkp/wkFOBwqu7R/07yWHiy53AObmuQf7KOVxk/gcovy6.jpg","profileStatus":"S","photoCnt":1,"likeCnt":0,"thumbnail":"http://t1.daumcdn.net/local/kakaomapPhoto/review/ecb4cc0bd2dc449eb2749e2eb56effc283e33167?original","kakaoMapUserId":"ajntok","platform":"kakaomap","photoList":["http://t1.daumcdn.net/local/kakaomapPhoto/review/ecb4cc0bd2dc449eb2749e2eb56effc283e33167?original"],"date":"2019.11.27.","isMy":false,"isBlock":false,"isEditable":false,"isMyLike":false},{"commentid":"1148851","contents":"음료맛도 괜찮아요","point":4,"username":"최군","profile":"http://th-p.talk.kakao.co.kr/th/talkp/wkCT3XhC9m/sTt2jOcnZabcT2zMXHDfzK/34nrcd.jpg","profileStatus":"S","photoCnt":0,"likeCnt":0,"kakaoMapUserId":"bgdt6s","platform":"kakaomap","date":"2019.10.10.","isMy":false,"isBlock":false,"isEditable":false,"isMyLike":false},{"commentid":"1046024","contents":"성산오르지말고 여기와요\n시원하고 진짜 경치 죽여줍니다","point":5,"username":"명태말린살","profile":"http://t1.daumcdn.net/local/kakaomapPhoto/profile/b44274d201a564636f4d02c732fd6a11cd1580de?original","profileStatus":"S","photoCnt":4,"likeCnt":0,"thumbnail":"http://t1.daumcdn.net/local/kakaomapPhoto/review/2e3f147cc81d02c03b21e0d6bcc0e0c91ec3c4f6?original","kakaoMapUserId":"kf1se6","platform":"kakaomap","photoList":["http://t1.daumcdn.net/local/kakaomapPhoto/review/2e3f147cc81d02c03b21e0d6bcc0e0c91ec3c4f6?original","http://t1.daumcdn.net/local/kakaomapPhoto/review/32b432f1a2660b02a1418479910e921ab358d783?original","http://t1.daumcdn.net/local/kakaomapPhoto/review/fd1b014997a202972a757284c50dc810be5cf48a?original","http://t1.daumcdn.net/local/kakaomapPhoto/review/00e5fa7380d4cf7778faaf4c24ccd1677a61e39a?original"],"date":"2019.08.31.","isMy":false,"isBlock":false,"isEditable":false,"isMyLike":false},{"commentid":"872801","contents":"성산 가기 귀찮을 때 가는것 추천","point":1,"username":"-","profile":"http://t1.daumcdn.net/local/kakaomapPhoto/profile/a5f8a2f9b0d90bd250db882939a59285c332e5d8?original","profileStatus":"S","photoCnt":0,"likeCnt":0,"kakaoMapUserId":"fu6vha","platform":"kakaomap","date":"2019.07.05.","isMy":false,"isBlock":false,"isEditable":false,"isMyLike":false},{"commentid":"570835","contents":"해질녘에 갔던지라 한적하고 좋았는데 숙소로 빨리 복귀하느라고 테이크아웃한게 아쉽네요. 일출뱅쇼 마셨는데 레몬+귤?+시나몬스틱 들어있어서 상큼한 시나몬 티 같은 느낌이었고 돌아가는 추운 길에 몸 데우기 좋았어요","point":5,"username":"otwosix","profile":"http://t1.daumcdn.net/local/kakaomapPhoto/profile/54b2fa28aff624f53e4f6b36ae0d054b1dd5cab0?original","profileStatus":"S","photoCnt":3,"likeCnt":0,"thumbnail":"http://t1.daumcdn.net/local/kakaomapPhoto/review/79a539eeac35dcb4aaf97bcdf3f57c0435a4edfc?original","kakaoMapUserId":"frm6t3","platform":"kakaomap","photoList":["http://t1.daumcdn.net/local/kakaomapPhoto/review/79a539eeac35dcb4aaf97bcdf3f57c0435a4edfc?original","http://t1.daumcdn.net/local/kakaomapPhoto/review/2973f68561b90be29711a43436fd373552ff50de?original","http://t1.daumcdn.net/local/kakaomapPhoto/review/17c5da002be47f92ec6b34f1703cd93901cbede1?original"],"date":"2019.05.21.","isMy":false,"isBlock":false,"isEditable":false,"isMyLike":false}]},"findway":{"x":484988,"y":-6869,"busDirectionCheck":false},"menuInfo":{"menucount":5,"menuList":[{"price":"15,000","menu":"코코넛 쉐이크 (ICE)"},{"price":"5,500","menu":"아메리카노"},{"price":"6,000","menu":"카페라떼"},{"price":"6,500","menu":"바닐라라떼"},{"price":"6,500","menu":"카라멜마끼아또"}],"productyn":"N","menuboardphotourlList":["http://t1.daumcdn.net/local/review/80066b443d8bc2a35887686484a354c987453aa066dfc67114ca9bf5fedf7433","http://t1.daumcdn.net/local/review/fd981a9a49f366ebb3965ecd72946d1e291824d26a4fc84fd33e6c2db1b06645"],"menuboardphotocount":12,"timeexp":"2019.11.05."},"photo":{"photoList":[{"photoCount":1566,"categoryName":"all","list":[{"photoid":"G","orgurl":"http://t1.daumcdn.net/place/98DAAB2CB28A46669FF0B142E2AA0B99"},{"photoid":"M","orgurl":"http://t1.daumcdn.net/place/13C0C0A938F74224B2E90F0E8CF5B99F"},{"photoid":"R2","orgurl":"http://t1.daumcdn.net/localfiy/1CDDF5C29CD9415FAA43A3A40B209C10"},{"photoid":"R3","orgurl":"http://t1.daumcdn.net/localfiy/26EA3EC56D964792ACCCE18E2B106D5D"},{"photoid":"R4","orgurl":"http://t1.daumcdn.net/localfiy/B11142DF4A354636950A2F10DB1589EE"}]},{"photoCount":7,"categoryName":"음식","list":[{"photoid":"TH345667099","orgurl":"http://postfiles1.naver.net/MjAxOTExMjNfODAg/MDAxNTc0NTE1MzU0MjE2.K6CwCrwYh9IkQc0v4YUHc6lUZslObgv71rynlbUZZT8g.rWw7e1CWaLW1Zvp8VuxFxLSAED2GsQr3fCwfHY55sqYg.JPEG.kaabdgg123/2019-08-12-17-58-32-061.jpg?type=w773"},{"photoid":"TH345667098","orgurl":"http://postfiles9.naver.net/MjAxOTExMjZfMTQx/MDAxNTc0NzQ5MTc3NTk0.HlZrPES_17x6ozhillaOhDYlb8lOc56hvrswXDfhVpwg.-mu1T23VNWcuLPpyy152B-L_PsqV5sZT7JGsiNnOaMYg.JPEG.kaabdgg123/SE-d0b77e1a-81aa-4a8f-9408-6e834754af86.jpg?type=w773"},{"photoid":"TH345667097","orgurl":"http://postfiles8.naver.net/MjAxOTExMjZfODUg/MDAxNTc0NzYxNDg5NjQ4.r1EIRhUxfsUngdfGmq_Ap-Rvxs9rZQRlkSwHdiFoWZog.kdk5M6oDG7aZtcMrsGOE-LTiDvUOBGJ8XYnowyCrHEwg.JPEG.kaabdgg123/SE-9b442e6b-2c89-4b59-bb97-20eb3b076ecf.jpg?type=w773"},{"photoid":"TH345667094","orgurl":"http://postfiles5.naver.net/MjAxOTExMjNfMTkw/MDAxNTc0NTE1MzQwOTAy.wUFuPtwkNxgUzp4mQOykeHuElju6F36ZBNgxB0N_VJwg.ShQCSLnwpYdZViKLdRGgBPKla2o_lzTNjdijLROuOEcg.JPEG.kaabdgg123/2019-08-12-17-58-24-301.jpg?type=w773"},{"photoid":"TH345667092","orgurl":"http://postfiles12.naver.net/MjAxOTExMjNfMTQx/MDAxNTc0NTE1MzQyMDU4.FMRfWTE_9FqFEuxYbpiDh8Y4vHyd7G2TGv9_LUY7i34g.0jL-WwMuWIbvtkKOernfaTLNjaYz8oVSr8TEx4vnAGgg.JPEG.kaabdgg123/2019-08-12-17-58-08-192.jpg?type=w773"}]},{"photoCount":12,"categoryName":"메뉴판","list":[{"photoid":"TE329273457","orgurl":"http://postfiles13.naver.net/MjAxOTA4MjZfMjY4/MDAxNTY2NzgyNzAxNzY0.Lb_CNKU8Cam8wjHeh1QyH_JbC63VVAhCzaIalFsIMBog.7oXojPhkh7TqlelZt2o95NDIleXhCkbGqxlMGwwFk-Yg.JPEG.rafiuta/SE-90673527-09df-45cd-87b7-fae89a1e4401.jpg?type=w966"},{"photoid":"TE329273456","orgurl":"http://postfiles8.naver.net/MjAxOTA4MjZfNjMg/MDAxNTY2NzgwMDU1Nzgw.hN_xWUgEd--VLBH5XAcGpsJLw5JkMX35eT8nts0GiA0g.uvSPX629ZO7yukPaBMy4PhT1Qwgs9oyetnGWPN5BRrkg.JPEG.rafiuta/IMG_2550.JPG?type=w966"},{"photoid":"TE329273455","orgurl":"http://postfiles5.naver.net/MjAxOTA4MjZfMjc5/MDAxNTY2NzgwMDU1MTEw.zmHpOqATGu5YtLSKluhRQqdGFnKsXwpmJL6mppWZsIUg.4lGZgvrlBUjLEoQYIMtnOLFbkNjCcw9VQZyVN9ZUymog.JPEG.rafiuta/IMG_2549.JPG?type=w966"},{"photoid":"TE317135409","orgurl":"http://postfiles7.naver.net/MjAxOTA2MTRfMjk3/MDAxNTYwNDk0NzI3NjE1.FPKxIFV7vAlbIUAUPfxyax8GgIpGgy9JV9WydwTvx20g.mfBsWCI_P_qMYWNkCUq6KZnJbcmR8NWdj9mGlbogN2Ug.JPEG.dhff58/14.jpg?type=w966"},{"photoid":"TE310904219","orgurl":"http://postfiles12.naver.net/MjAxOTA1MTFfOSAg/MDAxNTU3NTc1MjgxNTkx.DR6-VjGfxsaRZIxdh8Qjp50zVNs9QF7708egUJI38FAg.MkmkxyQD2Ife555PUh1-94deYlrI_bo7LowENLYcxPog.JPEG.yeonjoo123/IMG_7364.jpeg?type=w966"}]},{"photoCount":2,"categoryName":"실내","list":[{"photoid":"TD299111467","orgurl":"https://blogfiles.pstatic.net/MjAxOTAzMTFfMzMg/MDAxNTUyMzAwMDk3ODc0.IEIwQZZUJS8VVvUoPRizKdJvXDgicIwjfmwCDx9e_LIg.JSKlxQBS9QcDQzsUVsYHu9F9JVnWTi3MsEePNT95Xkkg.JPEG.conravi/a.jpg"},{"photoid":"TD298797495","orgurl":"http://postfiles3.naver.net/MjAxOTAzMDNfODAg/MDAxNTUxNTgwNDY2NTMx.CYdyYaiUnCYOiOvGsHdEAq_qtWpHGnItPRLBiypVQWog.VcfwCTVcD6ox4EpTizfS_ijdOlfyviMuOTDDl6BL9Wog.JPEG.pshyun6716/20190228_174600.jpg?type=w773"}]},{"photoCount":3,"categoryName":"기타","list":[{"photoid":"TA298797498","orgurl":"http://postfiles9.naver.net/MjAxOTAzMDNfMjE0/MDAxNTUxNTgwNDczMzQ2.tELRhTwCSwW7W7hqHZPInrvMKG-zxkvNV8jFyitUATAg.boAOdhX2Cx0MhC3sMEW99pTwBKbIg12yXUT6IdfZjJMg.JPEG.pshyun6716/20190228_174353.jpg?type=w773"},{"photoid":"TN345667090","orgurl":"http://postfiles10.naver.net/MjAxOTExMjNfMjMx/MDAxNTc0NTE1MzMzNzcz.9IOUtvcCtN8Q3jEEoCfowU8ZVVO1lWbWTgeebgtjdQEg.4B-E3Rp_L3U8PfX-VJpcpsNsd2t3N40fK8We7fJp6ogg.JPEG.kaabdgg123/2019-08-12-17-42-18-758.jpg?type=w773"},{"photoid":"TN314720001","orgurl":"https://blogfiles.pstatic.net/MjAxOTA1MzFfNjEg/MDAxNTU5MzEzMTgwNzcz.GvqMCAIRgbz1_8JJLuMX49E8zlZQPwJfCPCxh7QlIbcg.XP9sE4zRf4quzCCF2bO_8MQuaP3j-TUN_fwEV3ja72Ig.JPEG.jongy0644/IMG_E8046.JPG?type=w2"}]}]}}