{"isMapUser":false,"isExist":true,"basicInfo":{"cid":2083166873,"placenamefull":"바다위에코끼리","mainphotourl":"http://t1.daumcdn.net/place/A081A3E9AC794F85B3F6CFA271E210F4","phonenum":"070-4140-4832","address":{"newaddr":{"newaddrfull":"협재1길 27-6","bsizonno":"63011"},"region":{"name3":"한림읍 협재리","fullname":"제주특별자치도 제주시 한림읍 협재리","newaddrfullname":"제주특별자치도 제주시 한림읍"},"addrbunho":"1695"},"homepage":"https://www.instagram.com/jeju_baco","homepagenoprotocol":"www.instagram.com/jeju_baco","wpointx":323921,"wpointy":-25924,"roadview":{"panoid":1088975016,"tilt":8,"pan":286.0,"wphotox":324010,"wphotoy":-25949,"rvlevel":0},"cateid":"18162","catename":"테마카페","cate1name":"음식점","feedback":{"allphotocnt":3197,"blogrvwcnt":157,"kascnt":9,"comntcnt":13,"scoresum":49,"scorecnt":13},"openHour":{"periodList":[{"periodName":"영업기간","timeList":[{"timeName":"영업시간","timeSE":"11:00 ~ 20:00","dayOfWeek":"월,화,수,목,일"},{"timeName":"영업시간","timeSE":"11:00 ~ 21:00","dayOfWeek":"금,토"}]}],"realtime":{"holiday":"N","breaktime":"N","open":"Y","moreOpenOffInfoExists":"Y","datetime":"20191203150100","currentPeriod":{"periodName":"영업기간","timeList":[{"timeName":"영업시간","timeSE":"11:00 ~ 20:00","dayOfWeek":"월,화,수,목,일"}]}}},"communityList":[{"communitynoprotocol":"blog.naver.com/pyinjeju","community":"http://blog.naver.com/pyinjeju"}],"source":{"date":"2019.11.28."},"isStation":false},"s2graph":{"gender":{"labels":["남","여"],"data":[611,261]},"torosImpressionId":"toros_kakaomap_sim_base","day":{"labels":[0,1,2,3,4,5,6,7,8,9,10,11,12,13,14,15,16,17,18,19,20,21,22,23],"avg":[0,0,0,0,0,1,0,0,2,1,13,9,8,10,15,7,9,10,6,18,5,2,2,4],"monday":[4,0,0,0,0,0,0,0,0,0,4,16,2,4,28,8,0,0,0,0,0,6,2,6],"tuesday":[2,0,0,0,0,0,0,2,4,0,2,12,16,18,10,20,8,10,0,0,0,2,2,2],"wednesday":[0,0,0,0,0,0,0,0,2,0,0,2,0,0,2,8,10,36,2,22,14,0,2,0],"thursday":[0,0,0,0,0,0,0,0,2,0,0,0,0,8,2,2,0,0,0,54,2,6,2,0],"friday":[0,0,0,0,0,8,2,0,0,8,2,18,4,42,48,4,4,14,14,48,18,0,2,0],"saturday":[0,0,0,0,0,1,0,0,6,2,62,8,3,0,9,5,4,4,9,8,0,0,4,20],"sunday":[0,4,0,0,0,0,0,0,0,2,26,12,36,4,8,6,38,10,22,0,2,6,0,6],"max":62,"wheremax":"saturday"},"nearPlaceList":[{"placenamefull":"쉼표","photourl":"http://t1.daumcdn.net/cfile/240E773352A54EFB0A","confirmid":20465427,"catename":"카페"},{"placenamefull":"카페훤","photourl":"http://t1.daumcdn.net/localfiy/searchregister_1756867299","confirmid":1632912716,"catename":"카페"},{"placenamefull":"안녕협재씨","photourl":"http://t1.daumcdn.net/place/F7DFC29C1FA443559702136C589933AD","confirmid":1614966348,"catename":"한식"},{"placenamefull":"왓새우","photourl":"http://t1.daumcdn.net/place/99F833563ACB4F0580C0386AAF978DE0","confirmid":1210911629,"catename":"퓨전중식"},{"placenamefull":"협재바당","photourl":"http://t1.daumcdn.net/place/B07E2A9FBF324377938C5A4610D1A116","confirmid":1159806681,"catename":"한식"},{"placenamefull":"오리지날로맨스","photourl":"http://t1.daumcdn.net/place/F5FB6ACA92D74D3D94182885AF2D6A78","confirmid":1130369934,"catename":"카페"},{"placenamefull":"에이블랙","photourl":"http://t1.daumcdn.net/place/974D17EB299646ACB08125A37A2CE807","confirmid":245265626,"catename":"호프,요리주점"},{"placenamefull":"술시","photourl":"http://t1.daumcdn.net/place/2CE720A443FF4C31909BCBBCB17DC993","confirmid":1300928251,"catename":"일본식주점"},{"placenamefull":"카페모래알","photourl":"http://t1.daumcdn.net/place/FD6EF4259D114E23B46A06DB029E70EA","confirmid":685289703,"catename":"카페"}],"age":{"labels":["~20","30","40","50~"],"data":[700,100,44,28],"max":700},"status":"Y"},"blogReview":{"placenamefull":"바다위에코끼리","moreId":19112346,"blogrvwcnt":157,"list":[{"blogname":"채영이의 일기장","blogurl":"http://blog.naver.com/m_chae0","contents":"시험보기도 전에 급하게 현실도피성으로 끊은 제주행 티켓 그리고 시험 끝나고 바로 다녀왔지롱! 키키 여정 견문 감상이 잘 드러나게 기행문스타일로 기록하기 1일 금단영펜션 저녁 비행기로 가서 일정이 없었다 맛있는 거 옆에 맛있는 거 옆에 맛있는 거? 작년 제주도에서 먹은 딱새우회는 너무 비렸는데 이번 딱새우회는 너무 맛있었다... ㅎ 가게 바이 가게인듯 친구들이 방어회 진짜 맛있다했는데 솔직히 방어회는 목포가 레알임 목포 광주 제주에서 방어회 먹어봤는데 목포에서 먹은 방어회가 갑 오브 갑 오브 갑! ((목포부심)) 금단영펜션 제주특별자치도 제주시 한경면 금등리 658-8 엉엉 숙소 너무 좋아요ㅠㅠ 숙소 너무너무너무 좋아ㅠㅠ 방 가구가 한샘이고 이불이 이브자리에 세사리빙인 곳 첨 봄? 대신 무조","outlink":"http://blog.naver.com/m_chae0/221717409441","date":"2019.11.25.","reviewid":"19704559","title":"제주 여행 기행문","photoList":[{"orgurl":"http://postfiles7.naver.net/MjAxOTExMjVfOTAg/MDAxNTc0NjEzNTMzMDU4.tN01CY_ChTbxKVocE4H74CCHDqO1wYi8HFVUUEaeUnsg.EPjycouo0rCtCxNj-qwgVu29dxvEhvZMZfEYd8OcOT8g.JPEG.m_chae0/IMG_4334.JPG?type=w773"},{"orgurl":"http://postfiles14.naver.net/MjAxOTExMjVfMjM0/MDAxNTc0NjEzOTUyMDA0._1h4NqzqZCcZjuadEYHXQplsR6XeqOWRk4mSw7lLjoAg.ZBxxELy_k_HQmaox1-mKzYmqGuPPn4kJgzi5KjdxVVkg.JPEG.m_chae0/IMG_4335.JPG?type=w773"},{"orgurl":"http://postfiles4.naver.net/MjAxOTExMjVfMTM0/MDAxNTc0NjE0MDk2OTQ5.dKjk-FIImOQyldgmveACwgRxmCromHjI_YIPrgJru_Ag.Jd6oDcYjJFIrODssTqv9Z8dPgbFMujaNgozQ1DPN-LEg.JPEG.m_chae0/IMG_3627.jpg?type=w773"},{"orgurl":"http://postfiles10.naver.net/MjAxOTExMjVfNzcg/MDAxNTc0NjE0NTE2MDM1.PNyr-TurjEKaD8D1bfDtAbfYtVeUbjgfJJQ2Ub7GzRIg.ux3zFm9GR3ab8K_t6b__iE_-wiZyjxIPeuMvkCF2D_4g.JPEG.m_chae0/IMG_3915.jpg?type=w773"},{"orgurl":"http://postfiles6.naver.net/MjAxOTExMjVfMjc1/MDAxNTc0NjE0NzYwMjk4.X9B0IaJP0LOnp7YZem_p8foFilnOJ-cGIfkgbe-PXWsg.0U1GJk1cy-BspXYFL2jQYmoJKj1hj5wbAAEmNz0evbAg.JPEG.m_chae0/IMG_3919.jpg?type=w773"},{"orgurl":"http://postfiles7.naver.net/MjAxOTExMjVfMTkw/MDAxNTc0NjE0NzYwMjY5.eCpynNrS2q1xbtBYBuMDbaUkf175Js1PyZGAsxkspR4g.lk5BWoKlwR_zUG1sAlBsESsul95bSM1Yk89ee18sbyIg.JPEG.m_chae0/IMG_3917.jpg?type=w773"},{"orgurl":"http://postfiles1.naver.net/MjAxOTExMjVfODkg/MDAxNTc0NjE1MDAyMDkx.hDSV2T5S-v0NmCLy3N8VYklkVcHpgNOKvJRGXPYCp_Qg.F9x10cfGD9GZeAeZKHfQrH0yF5E5iExV203gLmIOad0g.JPEG.m_chae0/IMG_4039.jpg?type=w773"},{"orgurl":"http://postfiles3.naver.net/MjAxOTExMjVfNiAg/MDAxNTc0NjE1MDQ1OTIz.goJa5LrOfvO9JZyqsBAMVb_YzuB5AzjiqiFy0K1dzKAg.sDEmOLQ1H0-1JdzrBvHEQrOBR7bUH_g-dTdSC2oGHUgg.JPEG.m_chae0/IMG_4205.JPG?type=w773"},{"orgurl":"http://postfiles2.naver.net/MjAxOTExMjVfNjUg/MDAxNTc0NjE1MDg0OTYx.WDW8sVj7dSMeJbDzCgUlKRk77-Rw5hRZSrk-RN_xQrEg.8eNmyeR5B3_XDblsTe5OMNh6ldYTtOCpzd_WuGAcznAg.JPEG.m_chae0/IMG_4116.jpg?type=w773"}],"isMy":false},{"blogname":"웃어도 하루, 울어도 하루","blogurl":"http://blog.naver.com/tjdfl1983","contents":"바다뷰가 예쁜 협재 카페 바다위에코끼리 사진/글 이리꽃 다녀온지는 조금 지난 #제주협재카페 멀리 비양도가 보이는 협재포구쪽에 자리한 #협재카페 바다위에코끼리 포토존 바다뷰가 너무나도 예술인 #협재바다위에코끼리 제주 분위기좋은 카페 방문후기 올려보아요 :) 외관 #바다위에코끼리 #제주바코 카페 내부 카페 안에서도 제주 푸른바다가 잘보이는 제주 협재 카페 바코 우리일행은 통유리창 앞에 놓인 뷰~ 좋은 자리 찜꽁! 메뉴판 협재 바다위에코키리 메뉴판이에요. 이곳은 직접 만든 수제케이크 당큰케이크가 맛있기로 유명 안먹어볼수가 없겠쥬 :) 매장한켠에는 기념품샵도 함께 운영중 #제주기념품샵 보는것만으로도 꿀잼 아기자기 다양한 소품들이 한가득! 지름신 스멀 스멀 ~","outlink":"http://blog.naver.com/tjdfl1983/221715955440","date":"2019.11.23.","reviewid":"19693112","title":"제주 협재 카페 바다위에코끼리","photoList":[{"orgurl":"http://postfiles16.naver.net/MjAxOTA5MjRfMTQz/MDAxNTY5MjU0OTI2MDc5.iuYVzwdnNDbGXawO03ernS6zBDgyfbr_P31SrzTI8PIg.lc8ZiBWeKCW3yl1dcDpGfNpvwB09uRm2kyB70aISgRMg.JPEG.tjdfl1983/1569254315896.jpg?type=w966"},{"orgurl":"http://postfiles9.naver.net/MjAxOTA5MjRfMTIy/MDAxNTY5MjU0OTI3Mjcx.iQMlSjlNN7le5IbE_2quv7zuvKE3HBc7nHnf8nipna0g.1pqYu8B3xxGRgnZTA4b-3cbKfvjEBJjRubzuCVRjyqgg.JPEG.tjdfl1983/1569254359726.jpg?type=w966"},{"orgurl":"http://postfiles13.naver.net/MjAxOTExMjNfMjUw/MDAxNTc0NDY3NzUwOTI0.9aMOZWItMNr8m2FKnipoYrPajKScvAnWM0zIK55575Ug.J8zXGQTe5jq7uA6fHdf7eeJsOXvJ2mK31PSKF_GrgrQg.JPEG.tjdfl1983/1574467752615.jpg?type=w966"},{"orgurl":"http://postfiles13.naver.net/MjAxOTA5MjRfMjMx/MDAxNTY5MjU0OTI4ODE3.3bK-uY33t9qBcnypDqe4CvteVZ6q_PmJEqwXUEsJnxQg.zrVb6Kt7Nrq8u3mMPxpBqJbBLVW8XZxI1kudOj9F1Y0g.JPEG.tjdfl1983/1569254271524.jpg?type=w966"},{"orgurl":"http://postfiles8.naver.net/MjAxOTA5MjRfOTkg/MDAxNTY5MjU0MjMyMTE4.tTbvpvR9OUydMkZl63Z9f6woHGSu7xOAf1mOBtVhWwMg.aDU_D-4TadN1RDJt1uvrulSiFVj0yIxD2JYdRyaBMX0g.JPEG.tjdfl1983/20190805_153216.jpg?type=w966"},{"orgurl":"http://postfiles3.naver.net/MjAxOTA5MjRfMTMy/MDAxNTY5MjU0OTMwMTQy.Be5M2ga_AEDVdvuTo6K5hwwHgZngkNSz8f1evpeunscg.AillyVY5D7Lik2hWb1cy-5ReyKI6pkz-9e5Asb8dPV8g.JPEG.tjdfl1983/1569254479980.jpg?type=w966"},{"orgurl":"http://postfiles13.naver.net/MjAxOTA5MjRfMTE0/MDAxNTY5MjU0OTMwODcx.tkC7_XMRxpaS1UKRfl1SQU9loyd-NS-3Me_3gUgy2GYg.2HLbSFXpyZYGY51lTQSEIfNptfCREpuqKLdpAoXijQQg.JPEG.tjdfl1983/1569254548018.jpg?type=w966"},{"orgurl":"http://postfiles9.naver.net/MjAxOTA5MjRfMjUw/MDAxNTY5MjU0NjE4MzE0.ErJuU_LYFYBx59RAUz8E7eSNlNTBmotcO-zCnpvJ7L0g.uDUFhPDyF_SD2rIQG6TK3hj-QvbP5RgKGOE84c_qYzIg.JPEG.tjdfl1983/1569254584587.jpg?type=w966"},{"orgurl":"http://postfiles15.naver.net/MjAxOTA5MjRfMTY4/MDAxNTY5MjU0OTMxNjY1.IjthSgdlRZsgSbVkiJf_9_uwDMCOVdMGxWIaLwnWWo0g.dCNtV7_Uj_Kd2fDEiqt96O7NSQtot_ptsgSx0VA-6Fgg.JPEG.tjdfl1983/1569254522706.jpg?type=w966"},{"orgurl":"http://postfiles12.naver.net/MjAxOTA5MjRfMTky/MDAxNTY5MjU0OTMyNDM0.k_02Xex1qpaEgTvq7z8RdoN8u-Py0J1ROLy9TOobqKUg.9TbCdT8JHTMnCMbJ0_wd00StUJN-s--Xm5qIWRWCTJIg.JPEG.tjdfl1983/1569254652599.jpg?type=w966"}],"isMy":false},{"blogname":"일상 기록중","blogurl":"http://blog.naver.com/gml2760","contents":"가을 제주도여행 DAY 4 3박4일 제주도여행의 마지막일정! 공항가기 전까지 반나절 정도의 시간이 있어서 빠르게 움직여야 했었는데요 협재 쪽에 있었는데 넘 좋아서 떠나기가 아쉽더라는 ㅠㅠㅠㅠ 우무푸딩 제주도 가기 전에 꼭 가야지 했던 몇안되는 곳중에 하나에요 ㅋㅋ 호텔 체크아웃 하자마자 바로 목적지로 설정하구~ #우무푸딩 종류는 커스타드/말차/초코 세가지가 있구요 가격은 6,300원으로 동일! 요건 따로 포스팅했으니 궁금하신 분들은 요기로↓↓↓ [제주 우무] umu 말차푸딩 사고 협재해수욕장 우무 umu 수제푸딩 안녕하세요옹행복했던 3박 4일 가을 제주도 여행을 마치고 다시 현실로 복귀 ㅜㅜ낼... blog.naver.com 말차맛이 진하게 나면","outlink":"http://blog.naver.com/gml2760/221710160644","date":"2019.11.17.","reviewid":"19624459","title":"[제주도여행 DAY 4] 우무푸딩/협재해수욕장/협재칼국수/카페 바다위에코끼리","photoList":[{"orgurl":"http://postfiles13.naver.net/MjAxOTExMTdfNjcg/MDAxNTczOTU0NTA1OTgw.sDnIsiEhxtCLimm-qDwDgdgmOTxkphWSyFUhqQu26fYg.eec8DRtniIY164T3ISklh9U7D8-2OatJIrCEVeiGj4gg.JPEG.gml2760/1573954509350.jpg?type=w966"},{"orgurl":"http://postfiles5.naver.net/MjAxOTExMTdfMTE0/MDAxNTczOTU0NTA2Njcy.F_rupvs9qAlE5qsny7Zf1GmUE9VQI3L7V_s7peiB0r0g.vJRzw9O2QnKxbuj3JO6uIeYuyF6Aw-gX_DEHGv2UcjEg.JPEG.gml2760/1573954510074.jpg?type=w966"},{"orgurl":"https://dthumb-phinf.pstatic.net/?src=%22https%3A%2F%2Fblogthumb.pstatic.net%2FMjAxOTEwMTVfMjQ4%2FMDAxNTcxMTM0Mjg1MDI5.2me1w-mMomB4BoG52RGtSRvPmAyX3ztqPZ7aEsIMbaIg.fMZkMhAMgNFzUCBKu6hivDMUg_VTgE09TK4ItwF1lZ4g.JPEG.gml2760%2F1571134283058.jpg%3Ftype%3Dw2%22&type=ff500_300"},{"orgurl":"http://postfiles16.naver.net/MjAxOTExMTdfMzUg/MDAxNTczOTIwMDU5MzQx.95if4XgywCrHHQSBo7FouuUVFSOjKtjX3HcmcnRT7icg.xJ48X1mByQ44Qfvzt5VWOTFOB9qG9KLINbkQ7Xez6XYg.JPEG.gml2760/1573920061623.jpg?type=w966"},{"orgurl":"http://postfiles15.naver.net/MjAxOTExMTdfMTky/MDAxNTczOTIwMDYwMDU0.69armavoz_qRW-wvqbqQLGjX18GOroZBYr1pIMCZwlwg.7CivQARH_8gvUJ7eKkEDhRNdiFJMZSlPqr-647O4HjYg.JPEG.gml2760/1573920062347.jpg?type=w966"},{"orgurl":"http://postfiles14.naver.net/MjAxOTExMTdfMTgz/MDAxNTczOTIwMTIyNTMw.mcUQCMK4JejAfmQNusnbrrgdcjaaL4TIbIS6pDkCjFAg.X1kmFHr9fCcfzFa26ohhI1Jlb1QYnyA9uQGwYr8YMBUg.JPEG.gml2760/1573920124792.jpg?type=w966"},{"orgurl":"http://postfiles12.naver.net/MjAxOTExMTdfOTYg/MDAxNTczOTIwMTI0MDEw.IMK5dpMXSemgmXXK-bkqMNlIl5j_wfuH-IXQaC6nlawg.rYXg988dq7BFtj3itwyMYJe-j5I9RRDdDS6X_wCoLXkg.JPEG.gml2760/1573920126273.jpg?type=w966"},{"orgurl":"http://postfiles2.naver.net/MjAxOTExMTdfMTEw/MDAxNTczOTIwMTI0ODE5.FPQ3KCACyLmqempbhLMMIIOMJ8dsNRGt3uzadQKxvH8g.QbaVRgbPzh25ZivW3llrC70oNfV-af5XGa-ruRHMNpgg.JPEG.gml2760/1573920127056.jpg?type=w966"},{"orgurl":"http://postfiles4.naver.net/MjAxOTExMTdfMjU3/MDAxNTczOTIwMTI1NzA5.HrMVN6GW7BRJilZy_4A8SiAYLTP9wcAMZRVXyJZJ-AUg.5krBmWoBZuR4-kqJmt1q14MFKiBOytiX096z6PNm31Yg.JPEG.gml2760/1573920127958.jpg?type=w966"},{"orgurl":"http://postfiles13.naver.net/MjAxOTExMTdfMTc2/MDAxNTczOTIwMjQ3MDUw.eIufR3IMONb29Fi8iOGQKlsaOgUA4iIGXaEHK-A5CXUg.XJTswktabJyV-Q1GzXrJRQEtIOk7UXnyh3mWF0wAzmQg.JPEG.gml2760/1573920249136.jpg?type=w966"}],"isMy":false},{"blogname":"슈라미수의 하루 다이어리","blogurl":"http://blog.naver.com/aurore119","contents":"제주 협제카페추천 ; 바다위에 코끼리 안녕하세요! 오늘 카페는 말차를 좋아하는 분들께 아주 아주 추천해 드리고 싶은 곳이에요! Previous image Next image 외부 그 곳은 바로 협재 바다가 환히 보이는 '바다위에 코끼리' 입니다! 그리고 우리 쿠키언니가 일하는 곳이기도 하죠!>. 내부 아래사진은 우리 쿠키언니인건 안 비밀,,,?ㅋㅋㅋㅋㅋㅋㅋ 내부가 정말 귀여워요! 테이블이 많지 않아서 분위기도 공간도 여유 롭답니다! 메뉴판 메뉴판도 귀엽게 해놓고 옆에 양 사이드에 디저트 사진도 있어서 디저트 고르기에도 매우 도움이 되었답니다! ","outlink":"http://blog.naver.com/aurore119/221675042769","date":"2019.10.11.","reviewid":"19241451","title":"제주 협제카페추천 ; 바다위에 코끼리","photoList":[{"orgurl":"http://postfiles2.naver.net/MjAxOTEwMTFfNDEg/MDAxNTcwNzg5ODMwOTY3.choMs7mgd8GwD89fh5_mz-eliUy6n50ID43UGrvvGp4g.vth-5qve8KX3AFvtYJgGwa4HmQ2mKP6tHdzPA93PvU4g.JPEG.aurore119/KakaoTalk_20191011_190914646_06.jpg?type=w773"},{"orgurl":"http://postfiles6.naver.net/MjAxOTEwMTFfNTEg/MDAxNTcwNzg5ODMwOTYz.ZT11oP1_FOyizulsLCBLP-vDGQsOcwxRvp05kwBgm-Ug.vRMNnivN05MhOmeVRbLahV2EXq_nAM4YNbfGZ8AgmiIg.JPEG.aurore119/KakaoTalk_20191011_190914646_09.jpg?type=w773"},{"orgurl":"http://postfiles5.naver.net/MjAxOTEwMTFfNzYg/MDAxNTcwNzkwMDI1ODAw.LzUNtdM_pnG5XC8wsZo5UIGktwi1re43YAYY1cXYvu8g.9bgmKZXfY7APAoqCVbNATYfyh64F6z5ZPHIZa-XmMEIg.JPEG.aurore119/SE-35517ecc-0e6f-43af-b787-e5dbca96ef1d.jpg?type=w773"},{"orgurl":"http://postfiles2.naver.net/MjAxOTEwMTFfMjgx/MDAxNTcwNzg5OTU0NjYz.SqhLBacnC7vqIGIKqocL3SyxBBWiQ4U2oeG6MbqZUKkg.1TspNagwADH1h37ys7j2wclyyPGSjvM-INg-1IcWLpMg.JPEG.aurore119/KakaoTalk_20191011_190914646_13.jpg?type=w773"},{"orgurl":"http://postfiles11.naver.net/MjAxOTEwMTFfMTUz/MDAxNTcwNzkwMTQ3OTgy.jQwQFIdYlBdabv6ilifIbTW44GuSxKfuA_zCdERZ2yIg.b1BhVWt56x42pSA-kqnQifh-Rex1-frPvMv_wOF2K6Ig.JPEG.aurore119/SE-f37904f6-0b2b-4be4-a52d-3e14177ef35a.jpg?type=w773"},{"orgurl":"http://postfiles7.naver.net/MjAxOTEwMTFfMjg3/MDAxNTcwNzkwMTQ2OTk1.D7ZwfiA_hyqoEK1FZej-cT-u5upfUGk5ZhT8KVbfHc8g.it5_gSpkBfPtn8VCu3Znc6ehXO9ovjIsxw2_arbLs3Yg.JPEG.aurore119/SE-cd23cf51-cd9e-4958-b2d0-29c7bc6fc453.jpg?type=w773"},{"orgurl":"http://postfiles1.naver.net/MjAxOTEwMTFfMTcy/MDAxNTcwNzkwMjg0NTE3.Xw2G0Y7ngcM6Ui5JWtEcqhAuknvQKS5KCCSnI1HvrM0g.R-rv36doqBWlgEyrhVdK-PWkIYnxoDrftBG5HYAZ5a8g.JPEG.aurore119/SE-89f1716d-d02e-48c4-8fb3-baf7db0c867a.jpg?type=w773"},{"orgurl":"http://postfiles2.naver.net/MjAxOTEwMTFfNjUg/MDAxNTcwNzkwNjkyNzU5.DTxoHofvuKuWF3hk21QU9rr46Tx3coNvHbAusOEPNccg.3HQ7aAXBqCCWvE2l0Wiw-uWoSFcmpXXBsCCBOHt0-0og.JPEG.aurore119/SE-1b6ff3f0-cf85-4b0e-8b3a-0c6029c501f1.jpg?type=w773"},{"orgurl":"http://postfiles16.naver.net/MjAxOTEwMTFfOTMg/MDAxNTcwNzkwNjk0MTEw.vwd3aY_y2IKOiWTIz-c3-LCzKx1Ci3E7t9izIbYNiXEg.yhM9Q69JhMy8MeIBhRZEkEWKuhqUt2j_NaIpSU70TIwg.JPEG.aurore119/SE-cab9f5da-5f36-41c5-917f-60b4d1a29f7f.jpg?type=w773"},{"orgurl":"http://postfiles10.naver.net/MjAxOTEwMTFfMjYw/MDAxNTcwNzkwNjkxNjk1.XQnYaVQVcUPPQkEK8VnCW18JwSK57_CkTKX8764J-Vgg.4e70FsMx-_uQ97vRwWBGdBNRiwE0h8XVsxVDv_lDmPQg.JPEG.aurore119/SE-679aac2c-7741-417e-a832-02da50cc82c6.jpg?type=w773"}],"isMy":false},{"blogname":"休_다이어리","blogurl":"http://blog.naver.com/thdud1083","contents":"협재해수욕장 추석이 끝나고 갑자기 바다가 보고 싶어진 나,,, 그런 나를 데리고 엄마가 같이 가준다고 하여 간 협재 해수욕장! (이러니까 가족들이 나를 관광객 취급 하는구나,,,를 또 느꼈당) 우리 집은 화북인데 협재까지는 1시간 정도가 걸렸던 거 같다. 울 어무니,, 팔도 아픈데 데리구 가주었당...죄송 앤드 감사,,,♥ 월정리 해변과 금능해수욕장, 협재해수욕장, 김녕해수욕장, 함덕해수욕장 등 제주도에는 에메랄드색 바다를 볼 수 있는 해수욕장들이 있는데 우리는 그 중 협재해수욕장으로 갔다. 부산에서는 거의 볼 수 없는 에메랄드빛 바다,,,,☆ 진짜 제주도에 살 때는 이 예쁜 바다가 왜 그리도 안 예뻐 보였는지,, 내가 있는 제주도와 부산 모두 바다와 가까운 곳이라서 너무 좋은 것 같다. 진짜 바다 ","outlink":"http://blog.naver.com/thdud1083/221665993039","date":"2019.10.02.","reviewid":"19224203","title":"[2019.09.15.] 제주여행/협재해수욕장/바다위에코끼리","photoList":[{"orgurl":"http://postfiles5.naver.net/MjAxOTEwMDJfMjI1/MDAxNTY5OTkzNTg1NjE1.GbDOxJtMVxMPfwGLwncsAHP6xC-FzklAQ7sDqUnZY6Ag.G5XMKnzQII3z4_jQeBo6Vtm0L2lUz0j49BcujLIq2JQg.JPEG.thdud1083/1569993584507.jpg?type=w773"},{"orgurl":"http://postfiles15.naver.net/MjAxOTEwMDJfMTc1/MDAxNTY5OTkzNTg2NzY3.TNiUEtw8LFm5UxUQ3GzH0TLHyJ97fJqy34QirAZhoAgg.InCzejRYNaKnG_QuEGbcyXMjgOWxA8J77Vafs3xZ6W0g.JPEG.thdud1083/1569993585598.jpg?type=w773"},{"orgurl":"http://postfiles5.naver.net/MjAxOTEwMDJfMTEg/MDAxNTY5OTkzNTg3Njk5.1bKhWMxiJQqE9k7gC4VUga2LJFGoos3Yl-off4vd9Lkg.8HshDvoqcjft2fM9ga1_4F_FhbGUvO7xtoUZVKli5tAg.JPEG.thdud1083/1569993586663.jpg?type=w773"},{"orgurl":"http://postfiles14.naver.net/MjAxOTEwMDJfMjY1/MDAxNTY5OTkzNTkyNTgy.B3I_aYBmVbZftY_5ULnypAXEON5CaAO_PZtPMyKhZ5Mg.oKFSAbxtdsqsf3f-X8ZNMwCeVYXVSYgdEHDjDqApEIcg.JPEG.thdud1083/1569993591523.jpg?type=w773"},{"orgurl":"http://postfiles2.naver.net/MjAxOTEwMDJfNDEg/MDAxNTY5OTkzNTg5NTU2.U-PtjuEOy2D4zyUSBUUh_a7J5gihKjSx-S-9vmWMpbsg.8aHVg5Ieid4cLyK6Y_hHgYDHKuOFeFcGih9KOuNNym4g.JPEG.thdud1083/1569993588501.jpg?type=w773"},{"orgurl":"http://postfiles10.naver.net/MjAxOTEwMDJfMjM5/MDAxNTY5OTkzNTkwNjA2.z4aenjdTPVpfgRsqHHjWO_5zDMOzazMIhu9WX7okRQIg.MspHLD12S56FOc6QVF1YUhPtomZOXf8ZcVG-sPEmeqYg.JPEG.thdud1083/1569993589569.jpg?type=w773"},{"orgurl":"http://postfiles4.naver.net/MjAxOTEwMDJfMTk5/MDAxNTY5OTkzNTg4NjQ4.e-_DPKooFHmz0Zg2Hoc-PuZN30KW_rA9NJDU_b7y4awg.EEn8voj6rrbGRd3qrxklvlAuPh4gznF-ba-QrjE2Yn8g.JPEG.thdud1083/1569993587600.jpg?type=w773"}],"isMy":false},{"blogname":"뿜뿜이 일상 이야기","blogurl":"http://blog.naver.com/gijoe7","contents":"오늘은 협재해수욕장 카페 바다위에코끼리에 대해서 포스팅 할께요~ 바다위에 코끼리 운영시간은 매일 11:00 - 19:00첫 째주 셋째주 수요일 휴무이구요~ 반려동물 동반입장이 가능하다고 하네요~ 협재해수욕장 카페 바다위에코끼리는 약간 주택가 사이에 있는 애매한 위치의 카페였는데요~ 네비를 찍고 갔는데도 길이 정확하게 않나와서 약간 헷갈리더라구요~ 길을 지나쳐서 다시 돌아오다가 자세히보니까 elephant on the sea라는 문구가 건물에 보였었는데요~ 이놈의 제주도에 왜이리 비가 많이 오는지 날이 흐려서 잘 안보였네요~ ㅋㅋ 한림 카페 바다위에코끼리 입구인데요~ 입구는 옆문이라고 생각하시면 될것이 출입문이 옆문으로 되어있었는데요~ 이유는 이렇게 정면에 바다가 바로 보이게 하려고 한거같아요~","outlink":"http://blog.naver.com/gijoe7/221657713606","date":"2019.09.27.","reviewid":"19112346","title":"한림 협재해수욕장 카페 바다위에코끼리를 다녀오다","photoList":[{"orgurl":"http://postfiles7.naver.net/MjAxOTA5MjRfMTM1/MDAxNTY5Mjg3ODUzNTUz.0Hp0lnlxjXYMvMVhdV74LmMGkqfjoD961YkJ2SpnRjQg.tjIHi9BrJjgiYB5oColxghrmjLG50CIasZPjk2lKqkog.JPEG.gijoe7/SE-4fbf26b0-c9f5-426a-b0ba-905347c8dca5.jpg?type=w966"},{"orgurl":"http://postfiles2.naver.net/MjAxOTA5MjRfMTIg/MDAxNTY5Mjg3ODU2MjE0.2pc8xQciqGEtBhoTy1GDqXmr_WXjJPywGx16JVAsCgog.skaHIg_5Hn89ZCfdYtrp2H-fKvbK4WLA8NyGhBSSIvIg.JPEG.gijoe7/SE-d17a12ab-08e8-4ac5-a895-c17139c344d4.jpg?type=w966"},{"orgurl":"http://postfiles9.naver.net/MjAxOTA5MjRfODEg/MDAxNTY5Mjg3ODU4OTIz.-3kjNZppKlcrQWL2KtzsaV_xCAE7iNCqZPZchPxpMXcg.WMLxlEdW18SW2V83kYH8xjBbfBilcO6VW5LDI0F-kxIg.JPEG.gijoe7/SE-1bd719a2-cc26-4f7c-bcc7-77666ae42ec2.jpg?type=w966"},{"orgurl":"http://postfiles1.naver.net/MjAxOTA5MjRfMjk2/MDAxNTY5Mjg3ODYxNDgw.B48U3sFqm_IaFbVALqpY8_5eWEjg6Rs2PnuXEpgSo44g.hzJfSZJWl7lGbOLMmfsZWT9PVDsvwppSabnxCdkrq7Eg.JPEG.gijoe7/SE-1faca47b-5a16-4a7d-8a4b-abb49a57ea2d.jpg?type=w966"},{"orgurl":"http://postfiles6.naver.net/MjAxOTA5MjRfNzYg/MDAxNTY5Mjg3ODY0MjE3.D22v9UExtQyWSCjU2M3jKEDnXPQERkdJcTSS8q91t9Ug.qr0TrDLBKv0-B1sNI3MsKaoAX0HQnM70mTnDkrXwDfwg.JPEG.gijoe7/SE-c7fdef17-cdc2-4fc0-912f-6c9e419fcde0.jpg?type=w966"},{"orgurl":"http://postfiles12.naver.net/MjAxOTA5MjRfMTgz/MDAxNTY5Mjg3ODY2ODc4.r33EQK8ZG41OGB_TE-DqZXYFtYmDAbx2zdkf20DOSG8g.SdUY5Rx0qlxJBQmhNZAxg1zm-yRhDNEQAfQMFXQJNpEg.JPEG.gijoe7/SE-20f9494e-9981-46a9-b9df-8b8039374f79.jpg?type=w966"},{"orgurl":"http://postfiles6.naver.net/MjAxOTA5MjRfMjg0/MDAxNTY5Mjg3ODY5NTYz.3v_n7n9Sfz6GXdu6iKG0vBBfgw_Y6cd7IOQzSj1sDcMg.FCyX2r97pdnYP7kPQb7IlTwxYRiaqgKwEQ4D_VXeIOMg.JPEG.gijoe7/SE-dcc5dcf0-b069-40b6-a593-90bd6e81f40f.jpg?type=w966"},{"orgurl":"http://postfiles6.naver.net/MjAxOTA5MjRfMTcy/MDAxNTY5Mjg3ODc0MzE1.ail8ZdTSpf4yFVf6i5xHoCEGubP3aGsekwXaQI6Ibx8g.oX1OR7b8wmk0YXRs1OWYCrXDMwBWeEU4n0DnyDjWToog.JPEG.gijoe7/SE-e74bff33-5eb8-46a4-98ff-3a97afd9fc7c.jpg?type=w966"},{"orgurl":"http://postfiles9.naver.net/MjAxOTA5MjRfODMg/MDAxNTY5Mjg3ODc3MjY2.en1U5twLgQMmPo2_bdgeFsqf6VkciVlqBaY3rMgXHoQg.dfn8OjD69WU1prO1a2Ql4sSPwA9p8srEL7Jz8t2G7sUg.JPEG.gijoe7/SE-7f008aa3-5611-4dfd-acc4-cf6d3033be7c.jpg?type=w966"},{"orgurl":"http://postfiles11.naver.net/MjAxOTA5MjRfMTgz/MDAxNTY5Mjg3OTE2MTgw.IemPjNghyYeYfPQigXRp5hwb5GowI98MpglJg-j4yWUg.Cb2AF122FXq4rawy00sdz7jJiEqjEUkH0ehVpiRCh4Qg.JPEG.gijoe7/SE-0de5385f-a078-4062-b8f7-aeab9f60e13d.jpg?type=w966"}],"isMy":false}]},"kakaoStory":{"placenamefull":"바다위에코끼리","moreId":"99244723390906259","kascnt":9,"list":[{"storyid":"102569582420169475","creator":"amy","outlink":"https://story.kakao.com/_HPFk70/IOxRZ95TUOA?from=kakaomap","image":"http://dn-l0-story.kakao.co.kr/dn/WxZWh/hyChLMpSLS/LkAPdrnwmXKlF2KgiUbpCk/img.jpg?width=1920&height=1920&avg=%2523a09394&v=2","imgcnt":9,"body":"점심먹고 들린 바닷가 까페. 환상적인 오션뷰에 제대로 힐링~ 아이스 봉봉라떼. 아이스 초코라떼. 아이스 아메. 치즈테린느2. 빵 굽는 냄새 맡으며 책도 읽고 캔들이랑 기념품 몇개 사옴^^","date":"2019.08.06."},{"storyid":"102569431627999074","creator":"amy","outlink":"https://story.kakao.com/_HPFk70/FYy8zLHRtn0?from=kakaomap","image":"http://dn-l0-story.kakao.co.kr/dn/gDOvp/hyCjVfyarh/U9kDmawEERmgtdY5woP5RK/img.jpg?width=1920&height=1920&avg=%2523a39597&v=2","imgcnt":8,"body":"점심먹고 들린 바닷가 까페. 환상적인 오션뷰에 제대로 힐링~ 아이스 봉봉라떼. 아이스 초코라떼. 아이스 아메. 치즈테린느.(넘 맛나서 하나 더) 빵 굽는 냄새 맡으며 책도 읽고 캔들이랑 기념품 몇개 사옴.","date":"2019.08.06."},{"storyid":"101557727452900307","creator":"앵두맘♥앵두공주(/^o^)/♡mihyun","outlink":"https://story.kakao.com/_61YDd3/kHWAC0tiaMA?from=kakaomap","image":"http://dn-l0-story.kakao.co.kr/dn/bJgj1w/hyz4KWa056/WjdMT5ZC9MrImt61tZOgYk/img.jpg?width=1280&height=1280&avg=%25237f838d&v=2","imgcnt":20,"body":"#앵두공주_10번째_제주여행 #앵두엄마_15번째_제주여행 - #제주여행 #제주 #제주도 #여행 #추억만들기 #한림 #협재 #협재해수욕장 #협재해변 #추억 #바다위에코끼리 #리얼딸기우유 #당근케이크 진짜 생딸기를 갈아넣은 맛난우유 #제주당근 으로 만든 폭신한 수제케이크 넘나 맛나효!! 울앵두랑도 쪼꼼 나눠먹어뜸^^ 울숙소 코앞인데 맘같아선 매일 오고시팡! 뷰가 엄청 예뻐효^^ 내가 그동안 가본 수많은 #해변카페 중에서도 손꼽힐정도로 매력있엉^^ #제주카페 #협재카페 #오션뷰 #카페 #반려견동반여행 #반려견동반카페 #애견동반여행 #애견동반카페 #앵두엄마_제주맛집 #앵두엄마_애정카페 - #앵두공주 #앵두엄마 ‍ #매일매순간_감사해_행복해_축복해_사랑해","date":"2019.02.08."},{"storyid":"100416819128172931","creator":"오재평","outlink":"https://story.kakao.com/_JXUkt/HBJMhoJjyJA?from=kakaomap","image":"http://dn-l0-story.kakao.co.kr/dn/dFP35a/hywQSaotww/LWkugvfWTiEvJCGkxVjTvk/img.jpg?width=1620&height=1080&avg=%2523878d5b&v=2","imgcnt":20,"body":"20180718~22 제주여행 Photo by JP 풍경..음식 #제주맛집 #천지연폭포 #협재해수욕장 #수영장괴물 야경사진 떨리네 삼각대 바꿔야겠다 렌즈 바꿔야겠다 #도두해녀의집 물회 맛있고 싱싱한게 보여 #기억나는집 해물탕 핵존맛..졸맛있어.. 옥돔구이는 쏘쏘 #제주김만복김밥 김밥이 유명한데 별로.. 비싸 #탐라갈치 갈치구이.조림.회 세트가있어 좋아 맛있어 #중문수두리보말칼국수 보말.성게칼국수.봉살죽 맛있어 #제주올레시장 이것저것 사다먹어 오메기떡. 마늘치킨... #제주흑돼지 바베큐 마트에서 사먹어 사진없어 마트에서 사도 비싸..소고기값... 근데 맛있어","date":"2018.07.22."},{"storyid":"100224172341066034","creator":"Beauty Therapist J","outlink":"https://story.kakao.com/_cYc9O3/gMzJP2TS4i0?from=kakaomap","image":"http://dn-l0-story.kakao.co.kr/dn/3rfLa/hywqGQkwOr/ux9M7Yfx9IOEYuRpRPKOUk/img.jpg?width=1080&height=1080&avg=%2523b9aeaa&v=2","imgcnt":3,"body":"덥따...ㅠㅠ 일땜에 나왔다가 너무 더워서 근처 커피숍으로 도망옴...ㅡㅠ 다행히... 요기 커피 맛나다~~~♡ #맛있는커피 #아포가토 #아메리카노 #아이스아메리카노 #아이스크림 #에스프레소 #제주 #바다위에코끼리","date":"2018.06.18."},{"storyid":"99244723390906259","creator":"김종호","outlink":"https://story.kakao.com/_FGwQe/j9CCDp4PNgA?from=kakaomap","image":"http://dn-l0-story.kakao.co.kr/dn/bJaoDj/hyucXTucuN/ci8QMSJv9U3Zsgm7NyYLpK/img.jpg?width=1080&height=1080&avg=%25236f7f8d&v=2","imgcnt":2,"body":"오랜만에 #제주도","date":"2017.12.27."}]},"comment":{"placenamefull":"바다위에코끼리","allComntcnt":13,"kamapComntcnt":10,"kaplaceComntcnt":3,"daumComntcnt":0,"scoresum":49,"scorecnt":13,"currentPage":1,"pageList":[1,2,3],"list":[{"commentid":"1082773","contents":"당근케이크로 유명하다지만 크림이 녹은 듯 하여 그다지 맛있지 않았어요, 비양도가 보이는 자리에 앉았는데 창틀 때문에 시야가 트이지 않고 답답한 느낌이 들었어요. 알바분이 친철해요 ","point":4,"username":"만쉐린 가이드","profile":"http://t1.daumcdn.net/local/kakaomapPhoto/profile/af9a80875bb73329c860580624be0745ab263089?original","profileStatus":"S","photoCnt":0,"likeCnt":0,"kakaoMapUserId":"e7o4fn","platform":"kakaomap","date":"2019.09.15.","isMy":false,"isBlock":false,"isEditable":false,"isMyLike":false},{"commentid":"975966","contents":"오픈 시간 전에 갔는데 불친절해서 바로 나왔어요. 오픈 시간 모르고 좀 일찍 도착한 손님한테 기다릴거면 기다리고 말라면 말아라라는 식은 좀 아니지 않나요;;;","point":1,"username":"이나리","profile":"http://t1.daumcdn.net/local/kakaomapPhoto/profile/7664e374859150bcb99c31183cc3c8165dc514d2?original","profileStatus":"S","photoCnt":0,"likeCnt":0,"kakaoMapUserId":"c8q91e","platform":"kakaomap","date":"2019.08.08.","isMy":false,"isBlock":false,"isEditable":false,"isMyLike":false},{"commentid":"786001","contents":"경치도, 인테리어도, 음식 맛도 모두 꽝... 당근케이크는 몇일 된 건지 크림이 굳어 딱닥한 느낌...","point":1,"username":"김현호","profile":"http://th-p.talk.kakao.co.kr/th/talkp/wkp5OR9q0p/WqWjWbdK9IDlUU8pvJMW3k/wais43.jpg","profileStatus":"S","photoCnt":0,"likeCnt":0,"kakaoMapUserId":"7kqkqm","platform":"kakaomap","date":"2019.06.09.","isMy":false,"isBlock":false,"isEditable":false,"isMyLike":false},{"commentid":"695437","contents":"사랑하는비양도","point":5,"username":"YUJIN","profile":"http://th-p.talk.kakao.co.kr/th/talkp/wk9hgD4W7y/4MV1utmbz7SGVT9BKLXYo1/h3b1gp.jpg","profileStatus":"S","photoCnt":1,"likeCnt":0,"thumbnail":"https://t1.daumcdn.net/local/review_placeapp/btqpEZw3RMd_sL049iKwv1nCMDuJio1bck_img.jpg","kakaoMapUserId":"10j60vv","platform":"kakaomap","photoList":["https://t1.daumcdn.net/local/review_placeapp/btqpEZw3RMd_sL049iKwv1nCMDuJio1bck_img.jpg"],"date":"2018.10.17.","isMy":false,"isBlock":false,"isEditable":false,"isMyLike":false},{"commentid":"198375","contents":"조용해서 좋았어요 당근케이크맛잇오요","point":5,"username":"미송","profile":"http://th-p.talk.kakao.co.kr/th/talkp/wkTPkBrHaB/2Cw2j0OKGDmkm03DtxPkO1/28jtxc.jpg","profileStatus":"S","photoCnt":0,"likeCnt":0,"kakaoMapUserId":"qm1e4a","platform":"kakaomap","date":"2018.08.09.","isMy":false,"isBlock":false,"isEditable":false,"isMyLike":false}]},"findway":{"x":323921,"y":-25924,"busstop":[{"busStopId":"BS40042","busStopName":"협재리","busStopDisplayId":"405001250","toBusstopDistance":162,"wpointx":324317,"wpointy":-26007,"busInfo":[{"busType":"간선","busTypeCode":"BLUE","busList":[{"busId":"B50744","busName":"202","busTextName":"(고산)(신성마을)"},{"busId":"B50745","busName":"202","busTextName":"(고산)(한라병원)"},{"busId":"B50754","busName":"202","busTextName":"(서귀포등기소)(신성마을,대정초등학교)"},{"busId":"B50750","busName":"202","busTextName":"(서귀포등기소)(신성마을,모슬포우체국)"},{"busId":"B50757","busName":"202","busTextName":"(서귀포등기소)(한라병원,대정초등학교)"},{"busId":"B50760","busName":"202","busTextName":"(서귀포등기소)(한라병원,모슬포우체국)"}],"busNames":"202"},{"busType":"지선","busTypeCode":"GREEN","busList":[{"busId":"B50309","busName":"784-1","busTextName":"(동광환승정류장)"},{"busId":"B54667","busName":"784-1","busTextName":"(동광환승정류장)(선인장마을,돌마을공원)"},{"busId":"B50707","busName":"784-2","busTextName":"(동광환승정류장)"}],"busNames":"784-1, 784-2"}]},{"busStopId":"BS40041","busStopName":"협재리","busStopDisplayId":"405001249","toBusstopDistance":213,"wpointx":324454,"wpointy":-25933,"busInfo":[{"busType":"간선","busTypeCode":"BLUE","busList":[{"busId":"B50769","busName":"202","busTextName":"(제주버스터미널)(산방산)"},{"busId":"B50768","busName":"202","busTextName":"(제주버스터미널)(산방산,대정고등학교)"},{"busId":"B50767","busName":"202","busTextName":"(제주버스터미널)(산방산,모슬포우체국)"},{"busId":"B50952","busName":"202","busTextName":"(제주버스터미널)(신성마을)"},{"busId":"B50771","busName":"202","busTextName":"(제주버스터미널)(안덕119센터,탄산온천)"},{"busId":"B50761","busName":"202","busTextName":"(제주버스터미널)(여의물,안덕119센터,산방산)"},{"busId":"B50766","busName":"202","busTextName":"(제주버스터미널)(여의물,안덕119센터,탄산온천)"},{"busId":"B50770","busName":"202","busTextName":"(제주버스터미널)(한라병원)"}],"busNames":"202"},{"busType":"지선","busTypeCode":"GREEN","busList":[{"busId":"B50306","busName":"784-1","busTextName":"(동명)"},{"busId":"B54668","busName":"784-1","busTextName":"(동명)(선인장마을,돌마을공원)"},{"busId":"B50317","busName":"784-2","busTextName":"(동명)"}],"busNames":"784-1, 784-2"}]}],"busDirectionCheck":true},"menuInfo":{"menucount":5,"menuList":[{"price":"5,000","menu":"아메리카노"},{"price":"5,500","menu":"카페라떼"},{"price":"6,500","menu":"크림 모카"},{"price":"6,000","menu":"밀크티"},{"price":"5,000","menu":"얼그레이"}],"productyn":"N","menuboardphotourlList":["http://t1.daumcdn.net/local/review/b3ab56abffb519f5d137be328038c8b342e19fc0772c0128c268d14b91610fc8","http://t1.daumcdn.net/local/review/6995d09bbca64ce1cde56726f6e5baf31f828c3625f50b8d46008ad315397547"],"menuboardphotocount":28,"timeexp":"2019.11.28."},"photo":{"photoList":[{"photoCount":3197,"categoryName":"all","list":[{"photoid":"G","orgurl":"http://t1.daumcdn.net/place/A081A3E9AC794F85B3F6CFA271E210F4"},{"photoid":"M","orgurl":"http://t1.daumcdn.net/place/2A238B71B6C14EBF9E8FBB3EAFBEAF72"},{"photoid":"P345405363","orgurl":"http://postfiles2.naver.net/MjAxOTExMjVfNjUg/MDAxNTc0NjE1MDg0OTYx.WDW8sVj7dSMeJbDzCgUlKRk77-Rw5hRZSrk-RN_xQrEg.8eNmyeR5B3_XDblsTe5OMNh6ldYTtOCpzd_WuGAcznAg.JPEG.m_chae0/IMG_4116.jpg?type=w773"},{"photoid":"P345405362","orgurl":"http://postfiles3.naver.net/MjAxOTExMjVfNiAg/MDAxNTc0NjE1MDQ1OTIz.goJa5LrOfvO9JZyqsBAMVb_YzuB5AzjiqiFy0K1dzKAg.sDEmOLQ1H0-1JdzrBvHEQrOBR7bUH_g-dTdSC2oGHUgg.JPEG.m_chae0/IMG_4205.JPG?type=w773"},{"photoid":"P345405361","orgurl":"http://postfiles1.naver.net/MjAxOTExMjVfODkg/MDAxNTc0NjE1MDAyMDkx.hDSV2T5S-v0NmCLy3N8VYklkVcHpgNOKvJRGXPYCp_Qg.F9x10cfGD9GZeAeZKHfQrH0yF5E5iExV203gLmIOad0g.JPEG.m_chae0/IMG_4039.jpg?type=w773"}]},{"photoCount":1,"categoryName":"음식","list":[{"photoid":"TG188715384","orgurl":"http://postfiles4.naver.net/MjAxNzA3MjhfNjcg/MDAxNTAxMjA5NjM2OTYz.Y_rPAwBabiYfHb3Jv3bA6VCmSyLr6rOuRLQbxgmLwPMg.htmrPZ_6o8RbTWzQmNhgSJccEHq_NB-QsUF81PprAB0g.PNG.deartoeun2/%ED%98%91%EC%9E%AC%EC%86%8C%ED%92%88%EC%83%B5.png?type=w2"}]},{"photoCount":28,"categoryName":"메뉴판","list":[{"photoid":"TE343781734","orgurl":"http://postfiles6.naver.net/MjAxOTExMTdfMzkg/MDAxNTczOTIwMjQ5NjE4.zUgyAbVDcfv9selBwMIQLt9Ihxf-6GxtQc964b_WkVEg.9NTbB1AUZjEswaGACYNYLSRheQtcbJI6VBGaLpxSlf8g.JPEG.gml2760/1573920251566.jpg?type=w966"},{"photoid":"TE335862166","orgurl":"http://postfiles1.naver.net/MjAxOTEwMTFfMTcy/MDAxNTcwNzkwMjg0NTE3.Xw2G0Y7ngcM6Ui5JWtEcqhAuknvQKS5KCCSnI1HvrM0g.R-rv36doqBWlgEyrhVdK-PWkIYnxoDrftBG5HYAZ5a8g.JPEG.aurore119/SE-89f1716d-d02e-48c4-8fb3-baf7db0c867a.jpg?type=w773"},{"photoid":"TE333157692","orgurl":"http://postfiles7.naver.net/MjAxOTA5MjRfMjk4/MDAxNTY5Mjg3OTI2NzAy.bewwxNYmv_SjXekBA4uLN9Vi8JNM2FNcnDYTDD9aPdEg.pFHdwzenybgCGNIb8Yz7QUZWEDyZhxuGWDD6Uu7ACZog.JPEG.gijoe7/SE-9b691b58-1f5d-41c1-bb3e-905e614418f4.jpg?type=w966"},{"photoid":"TE323864725","orgurl":"http://postfiles11.naver.net/MjAxOTA3MjNfMTYy/MDAxNTYzODg0MTE1Mjgz.ePp95gkKPXO8sufAWFH8u6n64yJ-wtuFwsotY0JcmNMg.NMaTEU9zMvUCyHtWysrlqtMv1a714gdKPdke5y4WLhwg.JPEG.wjdgodls0502/IMG_8636.jpg?type=w580"},{"photoid":"TE302083480","orgurl":"http://postfiles14.naver.net/MjAxOTAzMjNfMTY0/MDAxNTUzMzA4ODE5NTQw.BGYsNhaifcsJRCWvCiAcXldUaG8DpPgfC2tvvejgc4wg.-IhmakEa5DY8Z6qUBjObyGF02ZKHeQGYQfpDn3zSE1Qg.JPEG.gmldkgus/SE-57a8d6b8-cdd5-4524-aaa7-cfbd5bc8538a.jpg?type=w580"}]},{"photoCount":29,"categoryName":"전경","list":[{"photoid":"TC290137790","orgurl":"http://postfiles12.naver.net/MjAxOTAxMjhfOTAg/MDAxNTQ4NjQzNzk3ODU3.oauO9v3ZHTDu5jF9EiOfAKwAxcI5Ef55-wOS9IDVTqAg.L2wHkTvKzbJCYANE82f5a5c3Oxa3C5BZ7uJBp2ENUKQg.JPEG.soyeonmk/20180713_110457.jpg?type=w773"},{"photoid":"TC288741279","orgurl":"http://postfiles11.naver.net/MjAxOTAxMjFfMjkw/MDAxNTQ4MDQ3MjM2NzMy.sFlS-0XEFxsh_Acn8rUNks_qduXxoOhTa1ipCBKc9t0g.MImIhqocbEdScd_cj04jZxmDczuoMSibhVy7vwK5w-gg.PNG.raonthemapark/SE-47d0f46f-7924-450e-a7c6-9b9c3b3f933e.png?type=w966"},{"photoid":"TC267003815","orgurl":"http://postfiles8.naver.net/MjAxODA5MTVfNDYg/MDAxNTM3MDE5NTYyMjAy.lnn8b8YP70puu_xqjlHfgnqytZTQ0ovbjCEWTYiiAZog.-6rwID1nnuRfbWEwRsGDklQlJNv61L7RDBmX42hCgqMg.JPEG.dmschd2578/image_4652815461537018847454.jpg?type=w966"},{"photoid":"TC267071656","orgurl":"http://postfiles14.naver.net/MjAxODA5MjBfMTk1/MDAxNTM3Mzk5MzUwNjk3.df6wJ83c3YeGLqlBKoZB577W0DXq2gomBfJxWkguLLIg.VODF3j3oiUhm1siYqlKR6UDItnoYieuFvhvnjX0sckQg.JPEG.lovesoftkiss/20180906_130650.jpg?type=w580"},{"photoid":"TC267071655","orgurl":"http://postfiles7.naver.net/MjAxODA5MjBfNjMg/MDAxNTM3Mzk5MzUxODIy.fEL82Qu9ulsn_NgUjPW3Lw-c8VK_q08R2kTEILbLAl4g.QrVGVBIGMb-CoSY70i0y9ywJI48cDTC7tB8ZiqciDI0g.JPEG.lovesoftkiss/20180906_130645.jpg?type=w580"}]},{"photoCount":41,"categoryName":"실내","list":[{"photoid":"TD294853996","orgurl":"http://postfiles8.naver.net/MjAxOTAyMTBfNDUg/MDAxNTQ5NzI3NTc3NDgw.pddXqt6_wejX8RxhfvoRabQUn0ER-iHjACO3C284mJIg.GWi5a4u2f4mqGYgXXNlN0KryRcPOc8dWPhaBYvM9jMUg.JPEG.jj0_0i/IMG_4768.jpg?type=w966"},{"photoid":"TD290137812","orgurl":"http://postfiles13.naver.net/MjAxOTAxMjhfMjI2/MDAxNTQ4NjQzODAzNDg4.kCzhnNQTXz-K3t-hdMSeG5Shw7t0Y0GZHifF_1L3WqYg.bkqz7ku014Bttj8UbysIthE1mNm2bVuu2UT_hhNXliog.JPEG.soyeonmk/20180713_113710.jpg?type=w773"},{"photoid":"TD290137801","orgurl":"http://postfiles13.naver.net/MjAxOTAxMjhfNDAg/MDAxNTQ4NjQzODA1NTMy.uRd3I5W7bGhGWK6o67YVOrcG8-wpfOh28xVdvgv5EZcg.0j8JPbudMMptgPh11DNJbuhW9VGDXNJ_nAJBgHek1NEg.JPEG.soyeonmk/20180713_110253.jpg?type=w773"},{"photoid":"TD267003787","orgurl":"http://postfiles5.naver.net/MjAxODA5MTVfMTg5/MDAxNTM3MDE5NDk0OTQx.89GDiUvF3xGz37ka0S_fHxj59fDfut3KfUQdmNwqIWog.TB8mMhvVCBByxsDblIG35XWCXBcYfZRg4gcmIt4ESwMg.JPEG.dmschd2578/image_7698782731537018847448.jpg?type=w966"},{"photoid":"TD263591773","orgurl":"http://postfiles16.naver.net/MjAxODA4MjZfNDcg/MDAxNTM1Mjc1NTMzNTM3.3hfGarL8GSVbkVJYiYgBLbXpylw-G0mZ-XMccghPn-cg.Rc3CN7ILI2ILkRrROlaXF4aXh9UeX-heO0rjTgA7oS8g.JPEG.psr909/P20180712_120803304_1462D9FE-69E6-44A7-AEAF-94EBCE7A5D06.JPG?type=w773"}]},{"photoCount":56,"categoryName":"기타","list":[{"photoid":"TB267003780","orgurl":"http://postfiles6.naver.net/MjAxODA5MTVfNTAg/MDAxNTM3MDE5NDY2MjI5.-0npEcWW4glfim6S-8mizGUngAqaREqwFZrPvpqbIa0g.3AMWs6f-PirRE5z0uKoMN-cN5F0LiRYdN32sixo9bgcg.JPEG.dmschd2578/image_209847041537018847456.jpg?type=w966"},{"photoid":"TB267071657","orgurl":"http://postfiles6.naver.net/MjAxODA5MjBfMjc3/MDAxNTM3Mzk5NDM5OTQ1.QE7BK9Sn86QALpLkoI4KxkNlzGeJVXrslzrhwRNVZtMg.ZmrLAEPERExKJaeE8x_EGsyIo_2mwvsVg1GvvjBLzkgg.JPEG.lovesoftkiss/20180906_130640.jpg?type=w580"},{"photoid":"TB263591768","orgurl":"http://postfiles4.naver.net/MjAxODA4MjZfMjg0/MDAxNTM1Mjc1NTMyOTI5.TGG5mZuRqn2HbzIgiqEUANg-LiAVzqYhNSYlLtL_JyQg.lQgD_K7pyDGow1qk9XKjtCTLOGYaJsBZ4TwBkDK6G3Ug.JPEG.psr909/P20180712_121049236_E4C9AEB1-514B-4B94-B349-D96FA2485B76.JPG?type=w773"},{"photoid":"TB248724874","orgurl":"http://postfiles16.naver.net/MjAxODA0MTNfNDQg/MDAxNTIzNjAzODg1NDQ0._TV0bibp1uptZFuI2qaTPYs00rho0jKUZ7Hs6LTDbwMg.kuQZI8bGB4279ylaSmuOiDJtKyKQK7MbxS3Dr6DixJIg.JPEG.g_ny/image_6193879711523603261815.jpg?type=w773"},{"photoid":"TB248724873","orgurl":"http://postfiles13.naver.net/MjAxODA0MTNfMjIy/MDAxNTIzNjA0MDEyMzE2.cgiIiYgqUP676f_JNBE8qixFDZgBSttDoqzkC7jlje0g.PKV7GLUurjZYiW7x3Jlg73xcmDut4tOiWJFZlx99Uv8g.JPEG.g_ny/image_3717202221523603261844.jpg?type=w773"}]}]}}